Workbook

Sheet Engagement Dashboard
A1: DASHBOARD
A3: SESSION ACTIVITY | D3: MONTHLY PULSE RATINGS | G3: ACTIVE ALERTS
A4: Total Sessions Logged | B4: =COUNTA('Session Logs'!A3:A4997) -> 1 | D4: Avg Meeting Value (Q1 /5) | E4: =IFERROR(AVERAGE('Monthly Pulse Logs'!F3:F4997),"–") -> – | G4: Alert Type | H4: Threshold | I4: Current Value | J4: Status
A5: Sessions – This Month | B5: =COUNTIFS('Session Logs'!$E$3:$E$4997,">="&DATE(YEAR(TODAY()),MONTH(TODAY()),1),'Session Logs'!$E$3:$E$4997,"<="&TODAY()) -> 0 | D5: Avg Goal Progress (Q2 /5) | E5: =IFERROR(AVERAGE('Monthly Pulse Logs'!G3:G4997),"–") -> – | G5: Low Meeting Value | H5: < 3.0 avg | I5: =IFERROR(AVERAGE('Monthly Pulse Logs'!F3:F4997),"No data") -> No data | J5: =IF(ISNUMBER(I5),IF(I5<3,"🔴 ACTION NEEDED","✅ OK"),"–") -> –
A6: Unique Interns with Sessions | B6: =IFERROR(SUMPRODUCT(1/COUNTIF('Session Logs'!D3:D4997,'Session Logs'!D3:D4997)*('Session Logs'!D3:D4997<>"")),"–") -> – | D6: Avg Support Felt (Q3 /5) | E6: =IFERROR(AVERAGE('Monthly Pulse Logs'!H3:H4997),"–") -> – | G6: Low Goal Progress | H6: < 3.0 avg | I6: =IFERROR(AVERAGE('Monthly Pulse Logs'!G3:G4997),"No data") -> No data | J6: =IF(ISNUMBER(I6),IF(I6<3,"🔴 ACTION NEEDED","✅ OK"),"–") -> –
A7: Sessions with Concerns | B7: =COUNTIF('Session Logs'!K3:K4997,"Yes") -> 0 | D7: Avg Next-Step Clarity (Q4 /5) | E7: =IFERROR(AVERAGE('Monthly Pulse Logs'!I3:I4997),"–") -> – | G7: Low Support Felt | H7: < 3.0 avg | I7: =IFERROR(AVERAGE('Monthly Pulse Logs'!H3:H4997),"No data") -> No data | J7: =IF(ISNUMBER(I7),IF(I7<3,"🔴 ACTION NEEDED","✅ OK"),"–") -> –
A8: Avg Days Between Sessions | B8: – | D8: % Meeting 2x+ per Month | E8: =IFERROR((COUNTIF('Monthly Pulse Logs'!J3:J4997,"2")+COUNTIF('Monthly Pulse Logs'!J3:J4997,"3+"))/COUNTA('Monthly Pulse Logs'!J3:J4997),"–") -> – | G8: Overdue Sessions | H8: > 0 interns | I8: =COUNTIF('Intern Monitoring'!G4:G203,"Overdue – Book Now") -> 0 | J8: =IF(I8>0,"🟡 FOLLOW UP","✅ OK") -> ✅ OK
G9: Missed Sessions | H9: > 0 interns | I9: =COUNTIF('Intern Monitoring'!G4:G203,"Missed Session") -> 0 | J9: =IF(I9>0,"🔴 ACTION NEEDED","✅ OK") -> ✅ OK
G10: Concerns Flagged (Pulse) | H10: > 0 this month | I10: =COUNTIF('Monthly Pulse Logs'!M3:M4997,"Yes") -> 0 | J10: =IF(I10>0,"🔴 FOLLOW UP","✅ OK") -> ✅ OK
G11: Low 2x Meeting Rate | H11: < 60% of pairs | I11: =IFERROR((COUNTIF('Monthly Pulse Logs'!J3:J4997,"2")+COUNTIF('Monthly Pulse Logs'!J3:J4997,"3+"))/COUNTA('Monthly Pulse Logs'!J3:J4997),"No data") -> No data | J11: =IF(ISNUMBER(I11),IF(I11<0.6,"🟡 FOLLOW UP","✅ OK"),"–") -> –

Sheet Cohorts
A1: Cohort Name | B1: Start Date | C1: End Date | D1: Status | E1: Intern Count | F1: Notes
A2: Cohort 1 - 2026 | B2: 01/01/2026 | C2: 30/04/2026 | D2: Active | E2: =COUNTIF('Intern Profiles'!C4:C303,A2) -> 63 | F2: Q1 intake
A3: Cohort 2 - 2026 | B3: 01/05/2026 | C3: 31/08/2026 | D3: Planned | E3: =COUNTIF('Intern Profiles'!C4:C303,A3) -> 0 | F3: Q2 intake
A4: Cohort 3 - 2026 | B4: 01/09/2026 | C4: 31/12/2026 | D4: Planned | E4: =COUNTIF('Intern Profiles'!C4:C303,A4) -> 0 | F4: Q3 intake
B7: Active Cohort: | C7: =IFERROR(INDEX(A2:A4,MATCH("Active",D2:D4,0)),"No Active Cohort") -> Cohort 1 - 2026

Sheet Paste - Mentors
A1: 📥 PASTE MENTOR LISTING HERE (Workday Export — Monthly)
A2: Keep headers in row 3. Replace data from row 4 downwards each month.
A3: Employee ID | B3: Employee | C3: Available to Mentor | D3: Mentor Types | E3: Location Address - Country | F3: Franchise | G3: Supervisory Organization | H3: Cost Center | I3: Employee Type | J3: Job Family Group | K3: Job Title | L3: Worker's Tenure At Company | M3: Age Group | N3: Gender (Locale Sensitive) | O3: Race/Ethnicity (Locale Sensitive and Country Securable)
A4: 5183472 | B4: Gerald Maunda | C4: Yes | D4: Career Mentor | E4: Zambia | F4: FNB | G4: FNB Zambia Operations (Mubukwanu Mutiti (Inherited)) | H4: 55300003086 FNB Zambia Operations | I4: Full Time Employee | J4: Process, Operations and Administration | K4: Administration Assistant | L4: 4 year(s), 6 month(s), 23 day(s) | M4: 30 - 39 | N4: Male | O4: N/A (Zambia)
A5: 5495989 | B5: Bonolo Molebatsi | C5: Yes | D5: Career Mentor | E5: Botswana | F5: FNB | G5: FNB Botswana Channels (Mpho Nthutang) | H5: 501071600 FNB Botswana Kanye Branch | I5: Full Time Employee | J5: Sales and Client Services | K5: Sales and Service Consultant | L5: 3 year(s), 5 month(s), 23 day(s) | M5: 30 - 39 | N5: Female | O5: African (Botswana)
A6: 5009642 | B6: Otisitswe Faith Rathedi | C6: Yes | D6: Career Mentor Leadership Mentor | E6: Botswana | F6: FNB | G6: FNB Botswana Marketing and Communications (Peo Porogo) | H6: 5010152700 FNB Botswana Marketing and Communications | I6: Full Time Employee | J6: Marketing and Communication | K6: Marketing Manager | L6: 7 year(s), 8 month(s), 23 day(s) | M6: 30 - 39 | N6: Female | O6: African (Botswana)
A7: 5109140 | B7: Bydon Longwe | C7: Yes | D7: Career Mentor | E7: South Africa | F7: FNB | G7: FNB Chief Executive Office (Harry Kellan) | H7: 83300001939 FNB Executives | I7: Expatriate - In | J7: Process, Operations and Administration | K7: Chief Executive Officer Broader Africa | L7: 8 year(s), 0 month(s), 24 day(s) | M7: 50 - 59 | N7: Male | O7: African (South Africa)
A8: 4946073 | B8: Patrick Bontsibokae | C8: Yes | D8: Career Mentor | E8: Botswana | F8: FNB | G8: FNB Botswana Commercial (Tiro Kgasa) | H8: 5010160150 FNB Botswana Commercial SME Banking | I8: Full Time Employee | J8: Sales and Client Services | K8: Relationship Manager | L8: 6 year(s), 11 month(s), 12 day(s) | M8: 30 - 39 | N8: Male | O8: African (Botswana)
A9: 4997751 | B9: Caroline Kepaletswe | C9: Yes | D9: Career Mentor | E9: Botswana | F9: FNB | G9: FNB Rand Merchant Bank Botswana (Harriet Mlalazi) | H9: 5010160660 FNB Botswana Service Centre | I9: Full Time Employee | J9: Sales and Client Services | K9: Service Head | L9: 9 year(s), 8 month(s), 3 day(s) | M9: 40 - 49 | N9: Female
A10: 4714849 | B10: Chapita Mbuzi | C10: Yes | D10: Career Mentor | E10: Zambia | F10: FNB | G10: FNB Zambia Retail Segment (Chileshe Bwali-sakala) | H10: 55300016152 FNB Zambia Corporate Sales | I10: Full Time Employee | J10: Sales and Client Services | K10: Relationship Manager | L10: 12 year(s), 5 month(s), 23 day(s) | M10: 40 - 49 | N10: Male | O10: N/A (Zambia)
A11: 3872521 | B11: Wiza Phiri | C11: Yes | D11: Career Mentor | E11: Zambia | F11: FNB | G11: FNB Zambia Credit (Martin Mukonje) | H11: 55300003075 FNB Zambia Credit | I11: Full Time Employee | J11: Credit | K11: Credit Analyst | L11: 13 year(s), 9 month(s), 23 day(s) | M11: 30 - 39 | N11: Female
A12: 4930088 | B12: Retselisitsoe Sylvia Khet'semane | C12: Yes | D12: Career Mentor | E12: Lesotho | F12: FNB | G12: FNB Lesotho (Lehlohonolo Seitlheko) | H12: 51800000189 FNB Lesotho Pioneer Branch | I12: Full Time Employee | J12: Sales and Client Services | K12: Client Service Representative | L12: 9 year(s), 10 month(s), 23 day(s) | M12: 30 - 39 | N12: Female | O12: African (Lesotho)
A13: 4989171 | B13: Borethe Mogwe | C13: Yes | D13: Career Mentor | E13: Botswana | F13: FNB | G13: FNB Botswana Wealth (Tshepiso Scheffers) | H13: 5010160500 FNB Botswana Consumer Banking | I13: Full Time Employee | J13: Product | K13: Customer Value Proposition Manager | L13: 9 year(s), 9 month(s), 9 day(s) | M13: 30 - 39 | N13: Female | O13: African (Botswana)
A14: 4804473 | B14: Gofaone Mokalake | C14: Yes | D14: Career Mentor Leadership Mentor | E14: Botswana | F14: FNB | G14: FNB Botswana Executive Suite (Onkarabile Kono) | H14: 5010164200 FNB Botswana Client Services | I14: Full Time Employee | J14: Sales and Client Services | K14: Service Manager | L14: 10 year(s), 10 month(s), 23 day(s) | M14: 40 - 49 | N14: Female | O14: African (Botswana)
A15: 4868455 | B15: Tshepo Sentle | C15: Yes | D15: Career Mentor | E15: Botswana | F15: FNB | G15: FNB Botswana Commercial (Thapelo Kamodi) | H15: 5010717300 FNB Botswana Cash Plus | I15: Full Time Employee | J15: Sales and Client Services | K15: Cash Plus Banker | L15: 10 year(s), 9 month(s), 23 day(s) | M15: 30 - 39 | N15: Male
A16: 4873033 | B16: Collen Tshebo | C16: Yes | D16: Career Mentor Leadership Mentor Technical Mentor Transition Mentor Workplace Buddy | E16: Botswana | F16: FNB | G16: FNB Botswana Business Support WesBank (Goeme Ganetsang) | H16: 5010394500 FNB Botswana Business Support | I16: Full Time Employee | J16: Sales and Client Services | K16: Client Portfolio Analyst | L16: 10 year(s), 5 month(s), 9 day(s) | M16: 30 - 39 | N16: Male
A17: 2893622 | B17: Mothibi Tangane | C17: Yes | D17: Career Mentor | E17: Botswana | F17: FNB | G17: FNB Botswana Operations (Nonofo Molwane) | H17: 501070500 FNB Botswana Cash Centre | I17: Full Time Employee | J17: Process, Operations and Administration | K17: Cash Operations Manager | L17: 22 year(s), 7 month(s), 13 day(s) | M17: 40 - 49 | N17: Male
A18: 4633369 | B18: Chipo Mwenya | C18: Yes | D18: Career Mentor | E18: Zambia | F18: FNB | G18: FNB Zambia Retail Segment (Jeremiah Namitondo) | H18: 55300009179 FNB Zambia Choma Branch | I18: Full Time Employee | J18: Sales and Client Services | K18: Branch Manager | L18: 12 year(s), 8 month(s), 2 day(s) | M18: 30 - 39 | N18: Female
A19: 3246388 | B19: Phetso Ntsowe | C19: Yes | D19: Career Mentor Leadership Mentor | E19: Botswana | F19: FNB | G19: FNB Botswana Retail Banking (Boniface Seane) | H19: 5010292200 FNB Botswana Channels Head Office | I19: Full Time Employee | J19: Legal, Risk and Compliance | K19: Risk Manager | L19: 17 year(s), 6 month(s), 16 day(s) | M19: 40 - 49 | N19: Female
A20: 3330370 | B20: Likenkeng Lylian Morojele | C20: Yes | D20: Career Mentor | E20: Lesotho | F20: FNB | G20: FNB Lesotho (Fusi Sefatsane) | H20: 51800001851 FNB Lesotho Kingway Branch | I20: Full Time Employee | J20: Sales and Client Services | K20: Branch Manager | L20: 17 year(s), 3 month(s), 2 day(s) | M20: 30 - 39 | N20: Female | O20: African (Lesotho)
A21: 4739736 | B21: Neo Thebeng-Phuthego | C21: Yes | D21: Career Mentor | E21: Botswana | F21: FNB | G21: FNB Botswana Audit Management (Theetso Nkwe) | H21: 5010166100 FNB Botswana Audit | I21: Full Time Employee | J21: Legal, Risk and Compliance | K21: Senior Audit Manager | L21: 12 year(s), 2 month(s), 23 day(s) | M21: 40 - 49 | N21: Female
A22: 4827430 | B22: Stephinah Magetse | C22: Yes | D22: Career Mentor | E22: Botswana | F22: FNB | G22: FNB Botswana Channels (Benni Dikobe) | H22: 501073600 FNB Botswana Mall Branch | I22: Full Time Employee | J22: Sales and Client Services | K22: Branch Manager | L22: 11 year(s), 4 month(s), 25 day(s) | M22: 50 - 59 | N22: Female
A23: 3243605 | B23: Baile Corrigan | C23: Yes | D23: Career Mentor | E23: Botswana | F23: FNB | G23: FNB Rand Merchant Bank Botswana (Harriet Mlalazi) | H23: 5010342500 RMB Botswana Flow Risk | I23: Full Time Employee | J23: Capital Markets and Invest | K23: Global Market Head | L23: 10 year(s), 8 month(s), 11 day(s) | M23: 40 - 49 | N23: Female
A24: 5436346 | B24: Billy Samuel Mwape | C24: Yes | D24: Career Mentor Leadership Mentor Transition Mentor Workplace Buddy | E24: Zambia | F24: FNB | G24: FNB Zambia Chief Executive Office (Kapumpe Chola) | H24: 55300003079 FNB Zambia Information Technology | I24: Full Time Employee | J24: Technology | K24: Chief Information Officer | L24: 4 year(s), 6 month(s), 4 day(s) | M24: 40 - 49 | N24: Male | O24: N/A (Zambia)
A25: 5066220 | B25: Jj Jongman | C25: Yes | D25: Career Mentor | E25: Botswana | F25: FNB | G25: FNB Botswana Human Capital (Kaone Kopi) | H25: 5010152800 FNB Botswana Human Capital | I25: Full Time Employee | J25: Human Capital | K25: Human Capital Business Partner | L25: 8 year(s), 7 month(s), 23 day(s) | M25: 40 - 49 | N25: Male | O25: African (Botswana)
A26: 5385571 | B26: Mwamba Musambo | C26: Yes | D26: Career Mentor | E26: Zambia | F26: FNB | G26: FNB Zambia Chief Executive Office (Kapumpe Chola) | H26: 55300003061 FNB Zambia Retail Segment | I26: Full Time Employee | J26: Sales and Client Services | K26: Retail Banking Executive | L26: 5 year(s), 0 month(s), 27 day(s) | M26: 40 - 49 | N26: Female
A27: 5101646 | B27: Charity Mubitelela | C27: Yes | E27: Zambia | F27: FNB | G27: FNB Zambia Retail Segment (Mike Nyimbili) | H27: 55300003645 FNB Zambia Kasama Branch | I27: Full Time Employee | J27: Sales and Client Services | K27: Multi Skilled Consultant | L27: 8 year(s), 2 month(s), 0 day(s) | M27: 30 - 39 | N27: Female
A28: 4974220 | B28: Kgosi Modisaeman | C28: Yes | D28: Career Mentor Leadership Mentor Workplace Buddy | E28: Botswana | F28: FNB | G28: FNB Botswana Brokerage (Govern Maseba) | H28: 5010166400 FNB Botswana Brokerage | I28: Full Time Employee | J28: Finance | K28: Reconciliation Officer | L28: 8 year(s), 4 month(s), 23 day(s) | M28: 30 - 39 | N28: Male | O28: African (Botswana)
A29: 4904699 | B29: Mcintire Luke | C29: Yes | D29: Career Mentor | E29: Botswana | F29: FNB | G29: FNB Botswana Retail (One Molefe) | H29: 5010344300 FNB Botswana Wesbank Retail Segment | I29: Full Time Employee | J29: Sales and Client Services | K29: Business Development Officer | L29: 9 year(s), 7 month(s), 23 day(s) | M29: 30 - 39 | N29: Male | O29: African (Botswana)
A30: 5004608 | B30: Maleseli Lorraine Chefa | C30: Yes | D30: Leadership Mentor | E30: Lesotho | F30: FNB | G30: FNB Lesotho (Daniel Mohau) | H30: 51800001852 FNB Lesotho OPC | I30: Full Time Employee | J30: Process, Operations and Administration | K30: Team Leader Back Office | L30: 8 year(s), 10 month(s), 23 day(s) | M30: 30 - 39 | N30: Female | O30: African (Lesotho)
A31: 4846443 | B31: Kapumpe Chola | C31: Yes | D31: Career Mentor | E31: Zambia | F31: FNB | G31: FNB Broader Africa (Bydon Longwe) | H31: 55300004651 FNB Zambia FCC | I31: Full Time Employee | J31: Process, Operations and Administration | K31: Chief Executive Officer | L31: 11 year(s), 2 month(s), 18 day(s) | M31: 50 - 59 | N31: Female
A32: 4778561 | B32: Mike Nyimbili | C32: Yes | D32: Career Mentor | E32: Zambia | F32: FNB | G32: FNB Zambia Retail Segment (Njavwa Nakapizye) | H32: 55300003645 FNB Zambia Kasama Branch | I32: Full Time Employee | J32: Sales and Client Services | K32: Branch Manager | L32: 11 year(s), 9 month(s), 23 day(s) | M32: 30 - 39 | N32: Male
A33: 4846583 | B33: Alfred Mwanza | C33: Yes | D33: Career Mentor | E33: Zambia | F33: FNB | G33: FNB Zambia Compliance (Eugenius Hambokoma) | H33: 55300003087 FNB Zambia Compliance | I33: Full Time Employee | J33: Legal, Risk and Compliance | K33: Financial Crime Analyst | L33: 11 year(s), 0 month(s), 23 day(s) | M33: 30 - 39 | N33: Male
A34: 4847393 | B34: Ronald Mvula | C34: Yes | D34: Career Mentor | E34: Zambia | F34: FNB | G34: FNB Zambia Retail Segment (Kateule Musonda) | H34: 55300009187 FNB Zambia Lusaka Private Suite | I34: Full Time Employee | J34: Process, Operations and Administration | K34: Branch Administrator | L34: 11 year(s), 2 month(s), 18 day(s) | M34: 30 - 39 | N34: Male
A35: 3511235 | B35: Palesa Moeng | C35: Yes | D35: Career Mentor Leadership Mentor Technical Mentor Workplace Buddy | E35: Botswana | F35: FNB | G35: FNB Botswana Operations (Bookeditswe Matladi-Molebatsi) | H35: 5010343200 FNB Botswana RMB Operations | I35: Full Time Employee | J35: Finance | K35: Reconciliation Officer | L35: 13 year(s), 0 month(s), 23 day(s) | M35: 30 - 39 | N35: Female | O35: African (Botswana)
A36: 4784545 | B36: Lesego Nkepe | C36: Yes | D36: Career Mentor | E36: Botswana | F36: FNB | G36: FNB Botswana Retail (Serwalo Mabotho) | H36: 5010292200 FNB Botswana Channels Head Office | I36: Full Time Employee | J36: Sales and Client Services | K36: Service Manager | L36: 9 year(s), 6 month(s), 23 day(s) | M36: 30 - 39 | N36: Female
A37: 3244318 | B37: Lydia Oakile | C37: Yes | D37: Career Mentor | E37: Botswana | F37: FNB | G37: FNB Botswana Operations (Otile Olekantse) | H37: 5010123600 FNB Botswana Francistown Mini Cash Centre | I37: Full Time Employee | J37: Sales and Client Services | K37: Cash Centre Bulk Teller | L37: 18 year(s), 4 month(s), 23 day(s) | M37: 40 - 49 | N37: Female | O37: African (Botswana)
A38: 2815966 | B38: Kelebogile Disang | C38: Yes | D38: Career Mentor | E38: Botswana | F38: FNB | G38: FNB Botswana Commercial (Valentine Harward) | H38: 5010160140 FNB Botswana Commercial Sales P100M+ | I38: Full Time Employee | J38: Sales and Client Services | K38: Relationship Manager | L38: 24 year(s), 8 month(s), 21 day(s) | M38: 40 - 49 | N38: Female
A39: 3511847 | B39: Amantle Mphoeng | C39: Yes | D39: Career Mentor | E39: Botswana | F39: FNB | G39: FNB Botswana Operations (Lesego Tamajobe) | H39: 5010164100 FNB Botswana Call Centre | I39: Full Time Employee | J39: Sales and Client Services | K39: Service Manager | L39: 12 year(s), 8 month(s), 23 day(s) | M39: 30 - 39 | N39: Male
A40: 3506622 | B40: Tekolo Rasenyai | C40: Yes | D40: Career Mentor Leadership Mentor | E40: Botswana | F40: FNB | G40: FNB Botswana Enabler (Mike Rammelane) | H40: 5010151500 FNB Botswana Credit Head Office | I40: Full Time Employee | J40: Credit | K40: Credit Manager | L40: 16 year(s), 1 month(s), 23 day(s) | M40: 30 - 39 | N40: Female
A41: 5655552 | B41: Shana Machado | C41: Yes | D41: Career Mentor | E41: Mozambique | F41: FNB | G41: FNB Mozambique Retail (Nasser Meggi) | H41: 5150MOZ7100 FNB Mozambique Growth | I41: Full Time Employee | J41: Sales and Client Services | K41: Service Manager | L41: 2 year(s), 10 month(s), 9 day(s) | M41: 30 - 39 | N41: Female
A42: 3247449 | B42: Linda Nengwenani | C42: Yes | D42: Career Mentor | E42: South Africa | F42: FNB | G42: FNB Points of Presence (Jacques Ackerman) | H42: 771037100 FNB POP Branch Delivery Woodlands Boulevard | I42: Full Time Employee | J42: Sales and Client Services | K42: Universal Advisor | L42: 18 year(s), 8 month(s), 23 day(s) | M42: 40 - 49 | N42: Female | O42: African (South Africa)
A43: 3278212 | B43: Sachin Arjun | C43: Yes | D43: Career Mentor Leadership Mentor Workplace Buddy | E43: South Africa | F43: RMB | G43: FR Hyphen Sales and Solutions (Gerrie Butler (Inherited)) | H43: 23300002345 FR Hyphen Commercial and Client Management | I43: Full Time Employee | J43: Process, Operations and Administration | K43: Business Solutions Head | L43: 18 year(s), 9 month(s), 12 day(s) | M43: 40 - 49 | N43: Male | O43: Indian (South Africa)
A44: 3282961 | B44: Yvonne September | C44: Yes | D44: Career Mentor | E44: South Africa | F44: FNB | G44: FNB Commercial Credit (Lenashan Chetty) | H44: 34200005513 FNB Commercial Credit Public Sector | I44: Full Time Employee | J44: Credit | K44: Credit Head | L44: 10 year(s), 6 month(s), 23 day(s) | M44: 40 - 49 | N44: Female | O44: African (South Africa)
A45: 3290328 | B45: Poloko Makhosane | C45: Yes | D45: Career Mentor | E45: South Africa | F45: FNB | G45: FNB Points of Presence (Llewellyn Phillips) | H45: 771014200 FNB POP Branch Delivery Pretoria | I45: Full Time Employee | J45: Sales and Client Services | K45: Local Market Sales and Service Manager | L45: 18 year(s), 10 month(s), 8 day(s) | M45: 40 - 49 | N45: Female | O45: African (South Africa)
A46: 3292800 | B46: Marilaine de Lange | C46: Yes | D46: Career Mentor | E46: South Africa | F46: FNB | G46: FNB Commercial EFT (Hossain Ally) | H46: 68400009949 FNB Commercial EFT Product House | I46: Full Time Employee | J46: Sales and Client Services | K46: Service Manager | L46: 18 year(s), 9 month(s), 9 day(s) | M46: 30 - 39 | N46: Female | O46: White (South Africa)
A47: 3209105 | B47: Renusha Moodley | C47: Yes | D47: Career Mentor | E47: South Africa | F47: FNB | G47: FNB Chief Risk Office (Emma Mer) | H47: 39400001871 FNB Chief Risk Office Executive | I47: Full Time Employee | J47: Process, Operations and Administration | K47: Chief Operating Officer | L47: 19 year(s), 2 month(s), 2 day(s) | M47: 40 - 49 | N47: Female | O47: Indian (South Africa)
A48: 3251268 | B48: Wayne Fick | C48: Yes | D48: Career Mentor | E48: South Africa | F48: FNB | G48: FNB Loans (Alpheus Legodi) | H48: 79100001943 FNB Consumer Loans Product | I48: Full Time Employee | J48: Product | K48: Product Manager | L48: 19 year(s), 0 month(s), 23 day(s) | M48: 40 - 49 | N48: Male | O48: Coloured (South Africa)
A49: 3252965 | B49: Venothan Padayachee | C49: Yes | D49: Career Mentor | E49: South Africa | F49: RMB | G49: RMBSA Client Group Technology Application Support (Subhash Panday) | H49: 77800000MTY RMB - RMB Marketing Technology | I49: Full Time Employee | J49: Technology | K49: Scrum Master | L49: 18 year(s), 10 month(s), 8 day(s) | M49: 40 - 49 | N49: Male | O49: Indian (South Africa)
A50: 3262766 | B50: Pinkie Ngcobo | C50: Yes | D50: Career Mentor | E50: South Africa | F50: FNB | G50: FNB HSL (Mamazile Zikalala) | H50: 21200001437 HSL Middle Sub Segment | I50: Full Time Employee | J50: Process, Operations and Administration | K50: Administrator | L50: 7 year(s), 1 month(s), 23 day(s) | M50: 40 - 49 | N50: Female | O50: African (South Africa)
A51: 3199703 | B51: Zunairah Ismail | C51: Yes | D51: Career Mentor | E51: South Africa | F51: FNB | G51: CDO Kernel iNterfaceX (Leonna Pillay) | H51: 21800002561 CDO Kernel iNterfaceX Contact Centre | I51: Full Time Employee | J51: Product | K51: Product Support Specialist | L51: 18 year(s), 7 month(s), 23 day(s) | M51: 40 - 49 | N51: Female | O51: Indian (South Africa)
A52: 3210103 | B52: Johan Terblanche | C52: Yes | D52: Career Mentor | E52: South Africa | F52: FNB | G52: CDO Infrastructure and Security Services (Grant Hassett) | H52: 20700001974 CDO Infrastructure and Security Services Information Security Management | I52: Full Time Employee | J52: Legal, Risk and Compliance | K52: IT Governance Specialist | L52: 18 year(s), 11 month(s), 8 day(s) | M52: 50 - 59 | N52: Male | O52: White (South Africa)
A53: 3252396 | B53: Diran Gajoo | C53: Yes | D53: Career Mentor | E53: South Africa | F53: FNB | G53: FNB Chief Risk Office Executive (Brandon Olivier) | H53: 39400004555 FNB Chief Risk Office Screening Services COO | I53: Full Time Employee | J53: Process, Operations and Administration | K53: Operations Head | L53: 13 year(s), 2 month(s), 3 day(s) | M53: 40 - 49 | N53: Male | O53: Indian (South Africa)
... A67: 3083713 | B67: Themba Twala | C67: Yes | D67: Career Mentor | E67: South Africa | F67: FNB | G67: FNB Commercial Sales Gauteng South and Central (Nicholas Nkomo) | H67: 34300006534 FNB Commercial Growth Gauteng South West South | I67: Full Time Employee | J67: Sales and Client Services | K67: Business Manager | L67: 20 year(s), 9 month(s), 23 day(s) | M67: 40 - 49 | N67: Male | O67: African (South Africa)
A68: 3084590 | B68: Wesley Pretorius | C68: Yes | E68: South Africa | F68: FNB | G68: FNB Chief Finance Office iFinance (Parmasivan Pillay) | H68: 39400001999 FNB Finance | I68: Full Time Employee | J68: Data and Analytics | K68: Chief Data and Analytics Officer | L68: 20 year(s), 8 month(s), 23 day(s) | M68: 40 - 49 | N68: Male | O68: White (South Africa)
A69: 2879573 | B69: Vutlhari Sithole | C69: Yes | D69: Career Mentor | E69: South Africa | F69: FNB | G69: FNB Points of Presence (Heather Rossouw) | H69: 7710891900 FNB POP Operations Implementation Mngrs | I69: Full Time Employee | J69: Process, Operations and Administration | K69: Implementation Manager | L69: 22 year(s), 11 month(s), 23 day(s) | M69: 40 - 49 | N69: Female | O69: African (South Africa)
A70: 2978210 | B70: Narisha Govender | C70: Yes | D70: Career Mentor Leadership Mentor Technical Mentor Transition Mentor | E70: South Africa | F70: RMB | G70: RMBSA CDAO Data, Analytics and Business Intelligence (Prashant Rijhumal) | H70: 77800000FZM FZM - CB Finance FIM | I70: Full Time Employee | J70: Data and Analytics | K70: Chief Data and Analytics Officer | L70: 19 year(s), 5 month(s), 26 day(s) | M70: 40 - 49 | N70: Female | O70: Indian (South Africa)
A71: 3021173 | B71: Natasha Naidoo | C71: Yes | D71: Career Mentor | E71: South Africa | F71: FNB | G71: FNB HSL (Chris Labuschagne) | H71: 21200001436 FNB HSL | I71: Full Time Employee | J71: Product | K71: Product Head | L71: 19 year(s), 5 month(s), 23 day(s) | M71: 40 - 49 | N71: Female | O71: Indian (South Africa)
A72: 3021238 | B72: Ashwin Gobind | C72: Yes | D72: Career Mentor | E72: South Africa | F72: FNB | G72: FNB Personal Exco (Sashin Sookroo) | H72: 83100009547 FNB Connect EXCO | I72: Full Time Employee | J72: Process, Operations and Administration | K72: Chief Operating Officer | L72: 19 year(s), 5 month(s), 6 day(s) | M72: 40 - 49 | N72: Male | O72: Indian (South Africa)
A73: 3021467 | B73: Caiphus Nyuswa | C73: Yes | D73: Career Mentor | E73: South Africa | F73: FNB | G73: FNB Commercial Sales Gauteng South and Central (Kabelo Motheane) | H73: 34300006528 FNB Commercial Growth Gauteng East Eastern Ekurhuleni | I73: Full Time Employee | J73: Sales and Client Services | K73: Area Manager | L73: 8 year(s), 0 month(s), 2 day(s) | M73: 40 - 49 | N73: Male | O73: African (South Africa)
A74: 2694972 | B74: Jason Nader | C74: Yes | D74: Career Mentor Leadership Mentor | E74: South Africa | F74: FNB | G74: FNB Retail Cash Investments Chief Executive Office (Himal Parbhoo) | H74: 65100004404 FNB Premium Cash Investments Development | I74: Full Time Employee | J74: Sales and Client Services | K74: Business Development Head | L74: 27 year(s), 5 month(s), 23 day(s) | M74: 40 - 49 | N74: Male | O74: White (South Africa)
A75: 2862212 | B75: Reginald Mothubakgang | C75: Yes | D75: Career Mentor Leadership Mentor Transition Mentor | E75: South Africa | F75: FNB | G75: FNB Commercial Forex CVM (Cindy-Lee Mayes) | H75: 81800006277 FNB Commercial Forex Growth | I75: Full Time Employee | J75: Sales and Client Services | K75: National Sales Head | L75: 24 year(s), 3 month(s), 23 day(s) | M75: 40 - 49 | N75: Male | O75: African (South Africa)
A76: 2862638 | B76: Liza Jacobs | C76: Yes | D76: Career Mentor | E76: South Africa | F76: WesBank | G76: FNB Commercial Chief Executive Office ABF (Khantse Radebe) | H76: 30100007269 WB ABF Operations Head Office | I76: Full Time Employee | J76: Process, Operations and Administration | K76: Executive Personal Assistant | L76: 24 year(s), 1 month(s), 23 day(s) | M76: 50 - 59 | N76: Female | O76: White (South Africa)
A77: 2882590 | B77: Olerato Chimole | C77: Yes | D77: Career Mentor | E77: South Africa | F77: FNB | G77: FNB Points of Presence (Lerato Maponya) | H77: 771035900 FNB POP Branch Delivery Lephalale | I77: Full Time Employee | J77: Sales and Client Services | K77: Associate | L77: 8 year(s), 5 month(s), 20 day(s) | M77: 40 - 49 | N77: Female | O77: African (South Africa)
A78: 2938618 | B78: Mercia Fox-Fisher | C78: Yes | D78: Career Mentor | E78: South Africa | F78: FNB | G78: FNB Retail Judgemental Credit (Nevi Govender) | H78: 85500006814 RJC Head Office | I78: Full Time Employee | J78: Credit | K78: Credit Manager | L78: 22 year(s), 5 month(s), 22 day(s) | M78: 50 - 59 | N78: Female | O78: Coloured (South Africa)
A79: 2667509 | B79: Dwan Steyn | C79: Yes | D79: Career Mentor | E79: South Africa | F79: FNB | G79: FNB Points of Presence (Bernice O Reilly) | H79: 7710669900 FNB POP Branch Finance | I79: Full Time Employee | J79: Finance | K79: Financial Manager | L79: 14 year(s), 5 month(s), 13 day(s) | M79: 40 - 49 | N79: Female | O79: White (South Africa)
A80: 2703173 | B80: Dumisani Ntanzi | C80: Yes | D80: Career Mentor | E80: South Africa | F80: FNB | G80: REMS Real Estate Management Services (Eve Kathar) | H80: 22300002373 REMS Campus Security | I80: Full Time Employee | J80: Support Services | K80: Security Coordinator | L80: 18 year(s), 2 month(s), 23 day(s) | M80: 50 - 59 | N80: Male | O80: African (South Africa)
... A114: 3089509 | B114: Eni Tsamago | C114: Yes | D114: Career Mentor | E114: South Africa | F114: FNB | G114: FNB Retail Exco (WILSON DIKOBO) | H114: 85500006814 RJC Head Office | I114: Full Time Employee | J114: Credit | K114: Credit Head | L114: 11 year(s), 7 month(s), 13 day(s) | M114: 40 - 49 | N114: Female | O114: African (South Africa)
A115: 3004473 | B115: Raymond Tyler | C115: Yes | E115: South Africa | F115: FNB | G115: FNB Retail COO (Sthokozile Zwezwe (Inherited)) | H115: 69000015126 FNB COO LRC | I115: Full Time Employee | J115: Legal, Risk and Compliance | K115: Risk Manager | L115: 20 year(s), 10 month(s), 15 day(s) | M115: 40 - 49 | N115: Male | O115: Coloured (South Africa)
A116: 2991004 | B116: Tinyiko Ndlovu | C116: Yes | D116: Career Mentor Leadership Mentor Technical Mentor Transition Mentor Workplace Buddy | E116: South Africa | F116: FNB | G116: FNB Commercial Projects and Operations (Luchaan Zeelie) | H116: 34200008093 FNB Commercial Projects | I116: Full Time Employee | J116: Process, Operations and Administration | K116: Project Management Office Head | L116: 17 year(s), 8 month(s), 23 day(s) | M116: 40 - 49 | N116: Male | O116: African (South Africa)
A117: 3105857 | B117: Nomvula Luphoko | C117: Yes | D117: Career Mentor | E117: South Africa | F117: FNB | G117: FNB Points of Presence (Tshwarelo Malele) | H117: 7710110800 FNB POP Branch Delivery Kabokweni Plaza | I117: Full Time Employee | J117: Process, Operations and Administration | K117: Branch Administrator | L117: 20 year(s), 7 month(s), 23 day(s) | M117: 40 - 49 | N117: Female | O117: African (South Africa)
A118: 3068463 | B118: Verona Singh | C118: Yes | D118: Career Mentor | E118: South Africa | F118: FNB | G118: FNB Commercial Sales Gauteng South and Central (Caiphus Nyuswa) | H118: 34300006536 FNB Commercial Growth Gauteng South West Rand | I118: Full Time Employee | J118: Sales and Client Services | K118: Business Manager | L118: 20 year(s), 10 month(s), 23 day(s) | M118: 40 - 49 | N118: Female | O118: Indian (South Africa)
A119: 2765152 | B119: Reshmee Pillay | C119: Yes | D119: Career Mentor | E119: South Africa | F119: FNB | G119: FNB Commercial Sales Inland (Pelonolo Mafata) | H119: 34300009157 FNB Commercial Growth Mpumalanga Gold | I119: Full Time Employee | J119: Sales and Client Services | K119: Area Manager | L119: 25 year(s), 9 month(s), 5 day(s) | M119: 50 - 59 | N119: Female | O119: Indian (South Africa)
A120: 2887673 | B120: Neal Sokay | C120: Yes | D120: Career Mentor | E120: South Africa | F120: FNB | G120: FNB Retail COO (Janedrie Naidoo) | H120: 69000006171 FNB Retail Enterprise Project Management Office | I120: Full Time Employee | J120: Process, Operations and Administration | K120: Programme Manager | L120: 22 year(s), 11 month(s), 23 day(s) | M120: 50 - 59 | N120: Male | O120: Indian (South Africa)
A121: 2962233 | B121: Grant Pentelow | C121: Yes | D121: Career Mentor Technical Mentor | E121: South Africa | F121: FNB | G121: FNB Personal and Private IT (Sandy Pillay) | H121: 59600005436 FNB Personal and Private IT HR | I121: Full Time Employee | J121: Human Capital | K121: Learning and Development Manager | L121: 18 year(s), 10 month(s), 23 day(s) | M121: 50 - 59 | N121: Male | O121: White (South Africa)
A122: 2964457 | B122: Dash Naidoo | C122: Yes | D122: Career Mentor | E122: South Africa | F122: FNB | G122: FR Life Assurance (Lee Bromfield) | H122: 61500010269 FR Life CEO Office | I122: Full Time Employee | J122: Process, Operations and Administration | K122: Executive Head | L122: 11 year(s), 3 month(s), 23 day(s) | M122: 40 - 49 | N122: Male | O122: Indian (South Africa)
A123: 2745232 | B123: John Cronje | C123: Yes | D123: Leadership Mentor Technical Mentor | E123: South Africa | F123: FNB | G123: FNB Loans (Yaasin Nordien) | H123: 79100005608 FNB Consumer Loans Support Operations | I123: Full Time Employee | J123: Sales and Client Services | K123: Client Experience Manager | L123: 26 year(s), 5 month(s), 23 day(s) | M123: 40 - 49 | N123: Male | O123: White (South Africa)
A124: 2867001 | B124: Nhlanhla Ngcobo | C124: Yes | D124: Career Mentor | E124: South Africa | F124: FNB | G124: FNB Commercial Sales Inland (Themba Mabizela) | H124: 34200009214 FNB Commercial Sales Mpumalanga Regional | I124: Full Time Employee | J124: Sales and Client Services | K124: Regional Head | L124: 22 year(s), 3 month(s), 23 day(s) | M124: 40 - 49 | N124: Male | O124: African (South Africa)
A125: 2868970 | B125: Lefu Mofonedi | C125: Yes | D125: Career Mentor | E125: South Africa | F125: FNB | G125: FNB Central Finance (Junaid Bayat) | H125: 39400004642 FNB CFP HFM | I125: Full Time Employee | J125: Technology | K125: HFM Developer | L125: 21 year(s), 8 month(s), 23 day(s) | M125: 40 - 49 | N125: Male | O125: African (South Africa)
A126: 2741903 | B126: Llewellyn Phillips | C126: Yes | D126: Career Mentor | E126: South Africa | F126: FNB | G126: FNB Points of Presence (Dima Thaba) | H126: 7710237800 FNB POP Regional Office Gauteng North | I126: Full Time Employee | J126: Sales and Client Services | K126: Area Manager | L126: 26 year(s), 5 month(s), 23 day(s) | M126: 40 - 49 | N126: Male | O126: Indian (South Africa)
A127: 2770369 | B127: Michael Honeywell | C127: Yes | D127: Career Mentor | E127: South Africa | F127: FNB | G127: FNB Business Platform Niches (Morne Cronje) | H127: 34300009103 FNB Business Platform Niches | I127: Full Time Employee | J127: Sales and Client Services | K127: Sales Head | L127: 26 year(s), 0 month(s), 18 day(s) | M127: 50 - 59 | N127: Male | O127: White (South Africa)
... A184: 2954869 | B184: Boipelo Ndingwan | C184: Yes | D184: Career Mentor | E184: South Africa | F184: FNB | G184: FNB Points of Presence (Heather Rossouw) | H184: 7710891900 FNB POP Operations Implementation Mngrs | I184: Full Time Employee | J184: Process, Operations and Administration | K184: Implementation Manager | L184: 21 year(s), 8 month(s), 22 day(s) | M184: 40 - 49 | N184: Female | O184: African (South Africa)
A185: 3001008 | B185: Yasien Allie | C185: Yes | E185: South Africa | F185: FNB | G185: FNB Personal and Private IT (Megan De Saldanha) | H185: 59600005979 FNB Personal and Private IT Collections IT | I185: Full Time Employee | J185: Technology | K185: Test Analyst Manager | L185: 20 year(s), 4 month(s), 23 day(s) | M185: 40 - 49 | N185: Male | O185: Coloured (South Africa)
A186: 2752298 | B186: Lindsay Sullivan | C186: Yes | D186: Career Mentor | E186: South Africa | F186: FNB | G186: FNB Commercial Sales Kwa-Zulu Natal (Asheen Magjee) | H186: 34200006953 FNB Commercial Sales Shared Services KwaZulu Natal | I186: Full Time Employee | J186: Sales and Client Services | K186: Business Development Head | L186: 22 year(s), 9 month(s), 23 day(s) | M186: 40 - 49 | N186: Male | O186: White (South Africa)
A187: 2785811 | B187: Kunny Radile | C187: Yes | D187: Career Mentor | E187: South Africa | F187: FNB | G187: FNB Points of Presence (Kobus Steenkamp) | H187: 771022700 FNB POP Branch Delivery Frankfort | I187: Full Time Employee | J187: Sales and Client Services | K187: Associate | L187: 24 year(s), 9 month(s), 25 day(s) | M187: 50 - 59 | N187: Female | O187: African (South Africa)
A188: 2786451 | B188: Lee-Anne Holmes | C188: Yes | D188: Career Mentor | E188: South Africa | F188: FNB | G188: FRG Data and Analytics Office (Lian Van Oudheusden) | H188: 39400010972 FNB Chief Risk Office Credit Risk and Reporting | I188: Full Time Employee | J188: Process, Operations and Administration | K188: Senior Project Manager | L188: 6 year(s), 8 month(s), 23 day(s) | M188: 40 - 49 | N188: Female | O188: Coloured (South Africa)
A189: 2787717 | B189: Susan Brown | C189: Yes | D189: Career Mentor | E189: South Africa | F189: FNB | G189: FNB HSL (Madinga Dyasi) | H189: 21200001465 HSL Servicing and Collections Risk Variations | I189: Full Time Employee | J189: Process, Operations and Administration | K189: Operations Manager | L189: 13 year(s), 11 month(s), 23 day(s) | M189: 50 - 59 | N189: Female | O189: Coloured (South Africa)
A190: 2860538 | B190: Lou-Ann Oosthuizen | C190: Yes | D190: Career Mentor | E190: South Africa | F190: FNB | G190: FNB Points of Presence (Hein Hoffman) | H190: 771044800 FNB POP Branch Delivery Hyde Park | I190: Full Time Employee | J190: Process, Operations and Administration | K190: Branch Administrator | L190: 23 year(s), 4 month(s), 23 day(s) | M190: 40 - 49 | N190: Female | O190: White (South Africa)
A191: 2590573 | B191: Rodney Forbes | C191: Yes | D191: Career Mentor | E191: Namibia | F191: FNB | G191: FNB Namibia Chief Executive Office (Conrad Dempsey) | H191: 302000004623 FNB Namibia FCC | I191: Full Time Employee | J191: Process, Operations and Administration | K191: Chief Operating Officer | L191: 28 year(s), 9 month(s), 23 day(s) | M191: 40 - 49 | N191: Male | O191: Racially disadvantaged (Namibia)
A192: 2623293 | B192: Ilse Smuts | C192: Yes | D192: Career Mentor | E192: South Africa | F192: FNB | G192: FNB Retail Cash Investments Chief Executive Office (Himal Parbhoo) | H192: 65100004404 FNB Premium Cash Investments Development | I192: Full Time Employee | J192: Sales and Client Services | K192: Business Development Head | L192: 28 year(s), 1 month(s), 23 day(s) | M192: 50 - 59 | N192: Female | O192: White (South Africa)
A193: 2879050 | B193: Vimal Deonanan | C193: Yes | D193: Career Mentor | E193: South Africa | F193: FNB | G193: FNB Retail Cash Investments Chief Executive Office (Himal Parbhoo) | H193: 65100005631 FNB Premium Cash Investments Regional Managers | I193: Full Time Employee | J193: Sales and Client Services | K193: National Sales Manager | L193: 6 year(s), 6 month(s), 23 day(s) | M193: 40 - 49 | N193: Male | O193: Indian (South Africa)
A194: 2725207 | B194: Alicia Mcquire | C194: Yes | D194: Career Mentor | E194: South Africa | F194: FNB | G194: FNB Points of Presence (Lindiwe Mokoaleli) | H194: 7710861100 FNB POP IT Quality Assurance | I194: Full Time Employee | J194: Technology | K194: Test Analyst | L194: 26 year(s), 7 month(s), 23 day(s) | M194: 50 - 59 | N194: Female | O194: Coloured (South Africa)
A195: 2627388 | B195: Fred Du Plessis | C195: Yes | D195: Career Mentor | E195: South Africa | F195: FNB | G195: FNB Commercial Sales Gauteng North (Andile Ncoyini) | H195: 34200006503 FNB Commercial Sales Gauteng Midrand 10 to 60M | I195: Full Time Employee | J195: Sales and Client Services | K195: Sales Head | L195: 27 year(s), 3 month(s), 23 day(s) | M195: 40 - 49 | N195: Male | O195: White (South Africa)
A196: 2631806 | B196: Shiraz Mahomed | C196: Yes | D196: Career Mentor | E196: South Africa | F196: FNB | G196: FNB Commercial Cash (Shamit Nathoo) | H196: 25200004525 FNB Commercial Cash PH Finance | I196: Full Time Employee | J196: Finance | K196: Financial Manager | L196: 27 year(s), 11 month(s), 10 day(s) | M196: 40 - 49 | N196: Male | O196: Indian (South Africa)
A197: 2633647 | B197: Bontle Mofokeng | C197: Yes | D197: Career Mentor | E197: South Africa | F197: FNB | G197: FNB Personal Segment Advisory and Suites (Raihaan Nawaz) | H197: 97200005297 PSAS Premier Voice | I197: Full Time Employee | J197: Sales and Client Services | K197: Sales and Service Manager | L197: 18 year(s), 2 month(s), 23 day(s) | M197: 40 - 49 | N197: Female | O197: African (South Africa)
... A284: 3553051 | B284: Samasree Sagadavan | C284: Yes | D284: Career Mentor | E284: South Africa | F284: FNB | G284: CDO Kernel iNterfaceX (Benjamin Appalsamy) | H284: 21800005632 CDO Kernel iNterfaceX Records Managment | I284: Full Time Employee | J284: Data and Analytics | K284: Records Manager | L284: 14 year(s), 7 month(s), 23 day(s) | M284: 40 - 49 | N284: Female | O284: Indian (South Africa)
A285: 3555933 | B285: Tshidiso Noge | C285: Yes | E285: South Africa | F285: FNB | G285: FNB Points of Presence (Lungi Nsibanyoni) | H285: 7710437300 FNB POP Branch Delivery Constantia Kloof | I285: Full Time Employee | J285: Process, Operations and Administration | K285: Branch Controller | L285: 8 year(s), 7 month(s), 23 day(s) | M285: 30 - 39 | N285: Male | O285: African (South Africa)
A286: 3560643 | B286: Andries Shuping | C286: Yes | D286: Career Mentor | E286: South Africa | F286: FNB | G286: FNB Points of Presence (Brian Wellsted) | H286: 771042800 FNB POP Branch Delivery White River | I286: Full Time Employee | J286: Sales and Client Services | K286: Local Market Manager | L286: 16 year(s), 11 month(s), 23 day(s) | M286: 40 - 49 | N286: Male | O286: African (South Africa)
A287: 3571610 | B287: Yoesrie Bloys | C287: Yes | D287: Career Mentor | E287: South Africa | F287: FNB | G287: FNB Points of Presence (Calvin Ross) | H287: 7710106400 FNB POP Branch Delivery Vangate | I287: Full Time Employee | J287: Sales and Client Services | K287: Branch Delivery Support Advisor | L287: 11 year(s), 2 month(s), 23 day(s) | M287: 50 - 59 | N287: Male | O287: Coloured (South Africa)
A288: 3573958 | B288: Carl Rembold | C288: Yes | D288: Career Mentor Leadership Mentor Transition Mentor Workplace Buddy | E288: South Africa | F288: FNB | G288: REMS Real Estate Management Services (Keiasha Naidoo) | H288: 22300004879 REMS Build | I288: Full Time Employee | J288: Process, Operations and Administration | K288: Regional Infrastructure Manager | L288: 12 year(s), 5 month(s), 23 day(s) | M288: 40 - 49 | N288: Male | O288: White (South Africa)
...

Sheet Paste - Relationships
A1: 📥 PASTE RELATIONSHIP REPORT HERE (Workday Export — Monthly)
A2: Keep headers in row 3. Replace data from row 4 downwards each month.
A3: Mentor ID | B3: Mentor | C3: Purpose | D3: Mentor Type | E3: Mentor Employee Type | F3: Mentor Race | G3: Mentor Gender | H3: Mentor Age Group | I3: Mentor Supervisory Organization | J3: Mentor Location Country | K3: Mentor Franchise | L3: Mentor Cost Centre | M3: Mentor Job Title | N3: Mentor Tenure | O3: Mentor Job Family Group | P3: Mentee ID | Q3: Mentee | R3: Mentee Employee Type | S3: Mentee Race | T3: Mentee Gender | U3: Mentee Age Group | V3: Mentee Supervisory Organization | W3: Mentee Location Country | X3: Mentee Franchise | Y3: Mentee Cost Centre | Z3: Mentee Job Title | AA3: Mentee Tenure | AB3: Mentee Job Family Group | AC3: Mentorship Events | AD3: Start Date | AE3: End Date | AF3: Close Mentorship Reason
A4: 3246388 | B4: Phetso Ntsowe | C4: Develop your team leadership and self-leadership skills Train to be an effective leader | D4: Leadership Mentor | E4: Full Time Employee | G4: Female | H4: 40 - 49 | I4: FNB Botswana Retail Banking (Boniface Seane) | J4: Botswana | K4: FNB | L4: 5010292200 FNB Botswana Channels Head Office | M4: Risk Manager | N4: 16 - 20 Years | O4: Operational Risk | P4: 3509672 | Q4: Banyatsi Seeme | R4: Full Time Employee | S4: African (Botswana) | T4: Female | U4: 30 - 39 | V4: FNB Botswana Channels (Janet Morolong) | W4: Botswana | X4: FNB | Y4: 5010401100 FNB Botswana Mogoditshane Branch | Z4: Migration Official | AA4: 11 -15 Years | AB4: Client Experience and Value Management | AC4: Close Mentorship Event for Banyatsi Seeme with Phetso Ntsowe Create Mentorship Event for Banyatsi Seeme with Phetso Ntsowe Edit Mentorship Event for Banyatsi Seeme with Phetso Ntsowe | AD4: 45170 | AE4: 45351 | AF4: Mentee Withdrawal - Availability
A5: 5495989 | B5: Bonolo Molebatsi | D5: Career Mentor | E5: Full Time Employee | F5: African (Botswana) | G5: Female | H5: 30 - 39 | I5: FNB Botswana Channels (Mpho Nthutang) | J5: Botswana | K5: FNB | L5: 501071600 FNB Botswana Kanye Branch | M5: Sales and Service Consultant | N5: 3 - 5 Years | O5: Direct Sales | P5: 5549248 | Q5: Boago Thomas | R5: Full Time Employee | S5: African (Botswana) | T5: Female | U5: 30 - 39 | V5: FNB Botswana Channels (Lorato Mothibi) | W5: Botswana | X5: FNB | Y5: 5010401300 FNB Botswana Mochudi Branch | Z5: Migration Official | AA5: <1 Year | AB5: Client Experience and Value Management | AC5: Create Mentorship Event for Boago Thomas with Bonolo Molebatsi | AD5: 45125
A6: 3246388 | B6: Phetso Ntsowe | D6: Career Mentor | E6: Full Time Employee | G6: Female | H6: 40 - 49 | I6: FNB Botswana Retail Banking (Boniface Seane) | J6: Botswana | K6: FNB | L6: 5010292200 FNB Botswana Channels Head Office | M6: Risk Manager | N6: 16 - 20 Years | O6: Operational Risk | P6: 5599199 | Q6: Thuto Kofi (Terminated) | T6: Female | U6: 20 - 29 | W6: Botswana | AA6: <1 Year | AC6: Close Mentorship Event for Thuto Kofi (Terminated) with Phetso Ntsowe Create Mentorship Event for Thuto Kofi (Terminated) with Phetso Ntsowe Edit Mentorship Event for Thuto Kofi (Terminated) with Phetso Ntsowe | AD6: 45139 | AE6: 45351 | AF6: Mentee Withdrawal - Availability
A7: 3244121 | B7: Udah Otukile (Terminated) | C7: To help the employee in navigating their growth in the organisation as well as exploring various opportunities. | D7: Career Mentor | G7: Female | H7: 50 - 59 | J7: Botswana | N7: 6 - 10 Years | P7: 5389836 | Q7: Kabelo Sekoto | R7: Full Time Employee | S7: African (Botswana) | T7: Male | U7: 30 - 39 | V7: FNB Rand Merchant Bank Botswana (Therisanyo Masuga) | W7: Botswana | X7: FNB | Y7: 5010168800 FNB Botswana Corporate Segments | Z7: Product Analyst | AA7: 3 - 5 Years | AB7: Product Support, Development and Analysis | AC7: Create Mentorship Event for Kabelo Sekoto with Udah Otukile (Terminated) | AD7: 44835 | AE7: 45199
A8: 5066220 | B8: Jj Jongman | C8: To help ascend to a Managerial role or change portfolio from the current Premier Banker which is overwhelming. | D8: Career Mentor | E8: Full Time Employee | F8: African (Botswana) | G8: Male | H8: 40 - 49 | I8: FNB Botswana Human Capital (Kaone Kopi) | J8: Botswana | K8: FNB | L8: 5010152800 FNB Botswana Human Capital | M8: Human Capital Business Partner | N8: 6 - 10 Years | O8: Business Human Capital | P8: 5124387 | Q8: Pamela Ndlovu | R8: Full Time Employee | T8: Female | U8: 30 - 39 | V8: FNB Botswana Wealth (Donna Isaacs) | W8: Botswana | X8: FNB | Y8: 5010160210 FNB Botswana Retail Smart and Gold Sales | Z8: Premier Banker | AA8: 6 - 10 Years | AB8: Client Relationship Management | AC8: Create Mentorship Event for Pamela Ndlovu with Jj Jongman Edit Mentorship Event for Pamela Ndlovu with Jj Jongman Edit Mentorship Event for Pamela Ndlovu with Jj Jongman | AD8: 44927 | AE8: 45657
A9: 3246388 | B9: Phetso Ntsowe | C9: Career guidance Relationship building and networking. Manage a career transition. Develop leadership skills. | D9: Career Mentor | E9: Full Time Employee | G9: Female | H9: 40 - 49 | I9: FNB Botswana Retail Banking (Boniface Seane) | J9: Botswana | K9: FNB | L9: 5010292200 FNB Botswana Channels Head Office | M9: Risk Manager | N9: 16 - 20 Years | O9: Operational Risk | P9: 5179564 | Q9: Kefilwe Samson | R9: Full Time Employee | T9: Female | U9: 30 - 39 | V9: FNB Botswana Channels (Lebelelang Mabeo) | W9: Botswana | X9: FNB | Y9: 5010164100 FNB Botswana Call Centre | Z9: Sales Consultant | AA9: 6 - 10 Years | AB9: Direct Sales | AC9: Close Mentorship Event for Kefilwe Samson with Phetso Ntsowe Create Mentorship Event for Kefilwe Samson with Phetso Ntsowe Edit Mentorship Event for Kefilwe Samson with Phetso Ntsowe Edit Mentorship Event for Kefilwe Samson with Phetso Ntsowe | AD9: 45170 | AE9: 45351 | AF9: Mentor Withdrawal - Availability
A10: 5495989 | B10: Bonolo Molebatsi | C10: To take me the right department | D10: Career Mentor | E10: Full Time Employee | F10: African (Botswana) | G10: Female | H10: 30 - 39 | I10: FNB Botswana Channels (Mpho Nthutang) | J10: Botswana | K10: FNB | L10: 501071600 FNB Botswana Kanye Branch | M10: Sales and Service Consultant | N10: 3 - 5 Years | O10: Direct Sales | P10: 4773829 | Q10: Otlaadisa Mogosane | R10: Full Time Employee | T10: Male | U10: 30 - 39 | V10: FNB Botswana Channels (Nametsegang Muchina) | W10: Botswana | X10: FNB | Y10: 501073700 FNB Botswana Broadhurst Branch | Z10: Teller | AA10: 6 - 10 Years | AB10: Client Services Support and Delivery | AC10: Create Mentorship Event for Otlaadisa Mogosane with Bonolo Molebatsi | AD10: 45205 | AE10: 45260
A11: 3246388 | B11: Phetso Ntsowe | D11: Leadership Mentor | E11: Full Time Employee | G11: Female | H11: 40 - 49 | I11: FNB Botswana Retail Banking (Boniface Seane) | J11: Botswana | K11: FNB | L11: 5010292200 FNB Botswana Channels Head Office | M11: Risk Manager | N11: 16 - 20 Years | O11: Operational Risk | P11: 2700069 | Q11: Bontle Maeco | R11: Full Time Employee | T11: Female | U11: 50 - 59 | V11: FNB Botswana Channels (Rose Selema) | W11: Botswana | X11: FNB | Y11: 501071400 FNB Botswana Lobatse Branch | Z11: Teller Coordinator | AA11: >20 Years | AB11: Client Services Support and Delivery | AC11: Close Mentorship Event for Bontle Maeco with Phetso Ntsowe Create Mentorship Event for Bontle Maeco with Phetso Ntsowe Edit Mentorship Event for Bontle Maeco with Phetso Ntsowe | AD11: 45170 | AE11: 45351 | AF11: Mentee Withdrawal - Availability
A12: 3246388 | B12: Phetso Ntsowe | D12: Career Mentor | E12: Full Time Employee | G12: Female | H12: 40 - 49 | I12: FNB Botswana Retail Banking (Boniface Seane) | J12: Botswana | K12: FNB | L12: 5010292200 FNB Botswana Channels Head Office | M12: Risk Manager | N12: 16 - 20 Years | O12: Operational Risk | P12: 5042070 | Q12: Ivy Letus | R12: Full Time Employee | S12: Coloured (Botswana) | T12: Female | U12: 40 - 49 | V12: FNB Botswana Channels (Fiona Kasese) | W12: Botswana | X12: FNB | Y12: 5010150200 FNB Botswana Riverwalk Branch | Z12: Service Consultant | AA12: 6 - 10 Years | AB12: Client Experience and Value Management | AC12: Close Mentorship Event for Ivy Letus with Phetso Ntsowe Create Mentorship Event for Ivy Letus with Phetso Ntsowe Edit Mentorship Event for Ivy Letus with Phetso Ntsowe | AD12: 45170 | AE12: 45351 | AF12: Mentee Withdrawal - Availability
A13: 3246388 | B13: Phetso Ntsowe | D13: Transition Mentor | E13: Full Time Employee | G13: Female | H13: 40 - 49 | I13: FNB Botswana Retail Banking (Boniface Seane) | J13: Botswana | K13: FNB | L13: 5010292200 FNB Botswana Channels Head Office | M13: Risk Manager | N13: 16 - 20 Years | O13: Operational Risk | P13: 4773829 | Q13: Otlaadisa Mogosane | R13: Full Time Employee | T13: Male | U13: 30 - 39 | V13: FNB Botswana Channels (Nametsegang Muchina) | W13: Botswana | X13: FNB | Y13: 501073700 FNB Botswana Broadhurst Branch | Z13: Teller | AA13: 6 - 10 Years | AB13: Client Services Support and Delivery | AC13: Close Mentorship Event for Otlaadisa Mogosane with Phetso Ntsowe Create Mentorship Event for Otlaadisa Mogosane with Phetso Ntsowe | AD13: 45230 | AE13: 45260 | AF13: Mentee Withdrawal - Availability
A14: 3246388 | B14: Phetso Ntsowe | C14: MENTORSHIP | D14: Leadership Mentor | E14: Full Time Employee | G14: Female | H14: 40 - 49 | I14: FNB Botswana Retail Banking (Boniface Seane) | J14: Botswana | K14: FNB | L14: 5010292200 FNB Botswana Channels Head Office | M14: Risk Manager | N14: 16 - 20 Years | O14: Operational Risk | P14: 3506878 | Q14: Maipelo Daman | R14: Full Time Employee | T14: Female | U14: 30 - 39 | V14: FNB Botswana Channels (Mable Motsumi) | W14: Botswana | X14: FNB | Y14: 5010160300 FNB Botswana Airport Junction | Z14: Branch Delivery Sales and Service Team Leader | AA14: 16 - 20 Years | AB14: Direct Sales | AC14: Close Mentorship Event for Maipelo Daman with Phetso Ntsowe Create Mentorship Event for Maipelo Daman with Phetso Ntsowe | AD14: 45170 | AE14: 45351 | AF14: Mentee Withdrawal - Availability
A15: 3246388 | B15: Phetso Ntsowe | C15: mentorship | D15: Career Mentor | E15: Full Time Employee | G15: Female | H15: 40 - 49 | I15: FNB Botswana Retail Banking (Boniface Seane) | J15: Botswana | K15: FNB | L15: 5010292200 FNB Botswana Channels Head Office | M15: Risk Manager | N15: 16 - 20 Years | O15: Operational Risk | P15: 5000181 | Q15: Maureen Lucas | R15: Full Time Employee | S15: African (Botswana) | T15: Female | U15: 40 - 49 | V15: FNB Botswana Channels (Onneile Mogotsi) | W15: Botswana | X15: FNB | Y15: 501079200 FNB Botswana Kgale Branch | Z15: Sales and Service Consultant | AA15: 6 - 10 Years | AB15: Direct Sales | AC15: Close Mentorship Event for Maureen Lucas with Phetso Ntsowe Create Mentorship Event for Maureen Lucas with Phetso Ntsowe | AD15: 45170 | AE15: 45351 | AF15: Mentee Withdrawal - Availability
A16: 3246388 | B16: Phetso Ntsowe | D16: Leadership Mentor | E16: Full Time Employee | G16: Female | H16: 40 - 49 | I16: FNB Botswana Retail Banking (Boniface Seane) | J16: Botswana | K16: FNB | L16: 5010292200 FNB Botswana Channels Head Office | M16: Risk Manager | N16: 16 - 20 Years | O16: Operational Risk | P16: 3245489 | Q16: Masego Basupang | R16: Full Time Employee | S16: African (Botswana) | T16: Female | U16: 40 - 49 | V16: FNB Botswana Wealth (Tshepiso Scheffers) | W16: Botswana | X16: FNB | Y16: 5010209700 FNB Botswana Premier | Z16: Premier Banker | AA16: 16 - 20 Years | AB16: Client Relationship Management | AC16: Close Mentorship Event for Masego Basupang with Phetso Ntsowe Create Mentorship Event for Masego Basupang with Phetso Ntsowe | AD16: 45173 | AE16: 45565 | AF16: Mentee Withdrawal - Availability
A17: 2815966 | B17: Kelebogile Disang | C17: Career guidance. Better integration into a team/business unit. Deal with diversity and inclusion challenges. | D17: Career Mentor | E17: Full Time Employee | G17: Female | H17: 40 - 49 | I17: FNB Botswana Commercial (Valentine Harward) | J17: Botswana | K17: FNB | L17: 5010160140 FNB Botswana Commercial Sales P100M+ | M17: Relationship Manager | N17: >20 Years | O17: Client Relationship Management | P17: 5598613 | Q17: Kaone Malete | R17: Full Time Employee | S17: African (Botswana) | T17: Female | U17: 20 - 29 | V17: FNB Botswana Channels (Lorato Mothibi) | W17: Botswana | X17: FNB | Y17: 5010401300 FNB Botswana Mochudi Branch | Z17: Sales and Service Consultant | AA17: <1 Year | AB17: Direct Sales | AC17: Create Mentorship Event for Kaone Malete with Kelebogile Disang | AD17: 45166
A18: 3246388 | B18: Phetso Ntsowe | D18: Career Mentor | E18: Full Time Employee | G18: Female | H18: 40 - 49 | I18: FNB Botswana Retail Banking (Boniface Seane) | J18: Botswana | K18: FNB | L18: 5010292200 FNB Botswana Channels Head Office | M18: Risk Manager | N18: 16 - 20 Years | O18: Operational Risk | P18: 4972279 | Q18: Prince Mopipi (Terminated) | T18: Male | U18: 30 - 39 | W18: Botswana | AA18: 3 - 5 Years | AC18: Close Mentorship Event for Prince Mopipi (Terminated) with Phetso Ntsowe Create Mentorship Event for Prince Mopipi (Terminated) with Phetso Ntsowe | AD18: 45170 | AE18: 45351 | AF18: Mentee Resigned
A19: 3246388 | B19: Phetso Ntsowe | D19: Leadership Mentor | E19: Full Time Employee | G19: Female | H19: 40 - 49 | I19: FNB Botswana Retail Banking (Boniface Seane) | J19: Botswana | K19: FNB | L19: 5010292200 FNB Botswana Channels Head Office | M19: Risk Manager | N19: 16 - 20 Years | O19: Operational Risk | P19: 3243990 | Q19: Gaongalelwe Ikaneng | R19: Full Time Employee | T19: Female | U19: 40 - 49 | V19: FNB Botswana Channels (Kgotso Morei) | W19: Botswana | X19: FNB | Y19: 5010167100 FNB Botswana Main Branch | Z19: Multi Skilled Consultant | AA19: 16 - 20 Years | AB19: Client Experience and Value Management | AC19: Close Mentorship Event for Gaongalelwe Ikaneng with Phetso Ntsowe Create Mentorship Event for Gaongalelwe Ikaneng with Phetso Ntsowe | AD19: 45170 | AE19: 45351 | AF19: Mentee Withdrawal - Availability
A20: 3246388 | B20: Phetso Ntsowe | D20: Career Mentor | E20: Full Time Employee | G20: Female | H20: 40 - 49 | I20: FNB Botswana Retail Banking (Boniface Seane) | J20: Botswana | K20: FNB | L20: 5010292200 FNB Botswana Channels Head Office | M20: Risk Manager | N20: 16 - 20 Years | O20: Operational Risk | P20: 5367891 | Q20: Tebogo Sebobi | R20: Full Time Employee | T20: Male | U20: 30 - 39 | V20: FNB Botswana Channels (Kgomotso Wetshootsile) | W20: Botswana | X20: FNB | Y20: 5010167100 FNB Botswana Main Branch | Z20: Sales Consultant | AA20: 3 - 5 Years | AB20: Direct Sales | AC20: Close Mentorship Event for Tebogo Sebobi with Phetso Ntsowe Create Mentorship Event for Tebogo Sebobi with Phetso Ntsowe | AD20: 45170 | AE20: 45351 | AF20: Mentee Withdrawal - Availability
A21: 3246388 | B21: Phetso Ntsowe | D21: Leadership Mentor | E21: Full Time Employee | G21: Female | H21: 40 - 49 | I21: FNB Botswana Retail Banking (Boniface Seane) | J21: Botswana | K21: FNB | L21: 5010292200 FNB Botswana Channels Head Office | M21: Risk Manager | N21: 16 - 20 Years | O21: Operational Risk | P21: 3505766 | Q21: Amongie Kewakae | R21: Full Time Employee | T21: Female | U21: 40 - 49 | V21: FNB Botswana Channels (Kgomotso Wetshootsile) | W21: Botswana | X21: FNB | Y21: 5010167100 FNB Botswana Main Branch | Z21: Service Consultant | AA21: 16 - 20 Years | AB21: Client Experience and Value Management | AC21: Close Mentorship Event for Amongie Kewakae with Phetso Ntsowe Create Mentorship Event for Amongie Kewakae with Phetso Ntsowe | AD21: 45170 | AE21: 45351 | AF21: Mentee Withdrawal - Availability
A22: 3330370 | B22: Likenkeng Lylian Morojele | C22: I would like to learn more leadership skills in branches. | D22: Leadership Mentor | E22: Full Time Employee | F22: African (Lesotho) | G22: Female | H22: 30 - 39 | I22: FNB Lesotho (Fusi Sefatsane) | J22: Lesotho | K22: FNB | L22: 51800001851 FNB Lesotho Kingway Branch | M22: Branch Manager | N22: 16 - 20 Years | O22: Client Experience and Value Management | P22: 3869865 | Q22: Mapule Mosiuoa | R22: Full Time Employee | S22: African (Lesotho) | T22: Female | U22: 30 - 39 | V22: FNB Lesotho (Mamahao Andronicah Makhoa) | W22: Lesotho | X22: FNB | Y22: 51800002929 FNB Lesotho Retail | Z22: Schemes Coordinator | AA22: 11 -15 Years | AB22: Direct Sales | AC22: Create Mentorship Event for Mapule Mosiuoa with Likenkeng Lylian Morojele | AD22: 45170 | AE22: 45566
A23: 4946073 | B23: Patrick Bontsibokae | C23: Career guidance Broaden organizational knowledge Innovation | D23: Career Mentor | E23: Full Time Employee | F23: African (Botswana) | G23: Male | H23: 30 - 39 | I23: FNB Botswana Commercial (Tiro Kgasa) | J23: Botswana | K23: FNB | L23: 5010160150 FNB Botswana Commercial SME Banking | M23: Relationship Manager | N23: <1 Year | O23: Client Relationship Management | P23: 5598613 | Q23: Kaone Malete | R23: Full Time Employee | S23: African (Botswana) | T23: Female | U23: 20 - 29 | V23: FNB Botswana Channels (Lorato Mothibi) | W23: Botswana | X23: FNB | Y23: 5010401300 FNB Botswana Mochudi Branch | Z23: Sales and Service Consultant | AA23: <1 Year | AB23: Direct Sales | AC23: Create Mentorship Event for Kaone Malete with Patrick Bontsibokae | AD23: 45175 | AE23: 45175
A24: 4778561 | B24: Mike Nyimbili | D24: Leadership Mentor | E24: Full Time Employee | G24: Male | H24: 30 - 39 | I24: FNB Zambia Retail Segment (Njavwa Nakapizye) | J24: Zambia | K24: FNB | L24: 55300003645 FNB Zambia Kasama Branch | M24: Branch Manager | N24: 11 -15 Years | O24: Client Experience and Value Management | P24: 5173353 | Q24: Miyoba Moonga (Terminated) | T24: Female | U24: 30 - 39 | W24: Zambia | AA24: 3 - 5 Years | AC24: Create Mentorship Event for Miyoba Moonga (Terminated) with Mike Nyimbili | AD24: 45236 | AE24: 45249
A25: 3511480 | B25: Kagiso Tlhase (Terminated) | C25: TO LEARN. | D25: Career Mentor | F25: African (Botswana) | G25: Male | H25: 50 - 59 | J25: Botswana | N25: 11 -15 Years | P25: 5595541 | Q25: LILLIAN K EZEKIEL | R25: Fixed Term Contractor | S25: African (Botswana) | T25: Female | U25: 30 - 39 | V25: FNB Botswana Executive Suite (Onkarabile Kono) | W25: Botswana | X25: FNB | Y25: 5010160800 FNB Botswana Retail Operations | Z25: Administration Assistant | AA25: 3 - 5 Years | AB25: Administration | AC25: Create Mentorship Event for LILLIAN K EZEKIEL with Kagiso Tlhase (Terminated) | AD25: 44937 | AE25: 44937
A26: 5084725 | B26: Manuel Motabatshindi | C26: Transition to Systems Analyst job | D26: Career Mentor | E26: Full Time Employee | F26: African (South Africa) | G26: Male | H26: 30 - 39 | I26: CDO Kernel Integrations (Rudzani Nemusombori) | J26: South Africa | K26: FNB | L26: 79000005315 CDO Kernel Integrations | M26: Systems Analyst | N26: 6 - 10 Years | O26: Business/Systems Analysis | P26: 5309697 | Q26: Sifisosakhe Dube | R26: Full Time Employee | S26: African (South Africa) | T26: Male | U26: 30 - 39 | V26: FNB Private Banking and Advisory (Kurt Schurbohm) | W26: South Africa | X26: FNB | Y26: 34100007232 PB&A Service Suite Advisor Engagement | Z26: Private Service Advisor | AA26: 6 - 10 Years | AB26: Client Relationship Management | AC26: Close Mentorship Event for Sifisosakhe Dube with Manuel Motabatshindi Create Mentorship Event for Sifisosakhe Dube with Manuel Motabatshindi | AD26: 44935 | AE26: 45443 | AF26: Mentoring Needs Fulfilled
A27: 7552793 | B27: Theo Ngoma | C27: To fast-track career progression. To improve stakeholder engagement To assist in peer coaching and skills transfer. To align career path and skills training, learning and development. | D27: Career Mentor | E27: Full Time Employee | F27: African (South Africa) | G27: Female | H27: 30 - 39 | I27: CDO Infrastructure and Security Services (Ntswaki Lecage) | J27: South Africa | K27: FNB | L27: 20700005266 CDO Infrastructure and Security Services Command Centre | M27: Enterprise Systems Manager | N27: 3 - 5 Years | O27: System Design and Administration | P27: 5238730 | Q27: Tebogo Moorosi (Terminated) | S27: African (South Africa) | T27: Male | U27: 30 - 39 | W27: South Africa | AA27: 3 - 5 Years | AC27: Create Mentorship Event for Tebogo Moorosi (Terminated) with Theo Ngoma | AD27: 45047 | AE27: 45412
A28: 4942027 | B28: Shantal Reddy | C28: Programme duration is 7 months from Aug – Feb 24 (considering Dec/Jan holidays) Mentees are expected to meet with their mentors at least once a month. Also, an additional 1 day “leave no action” a month aimed at job shadowing virtually or face to face. Mentees are expected to take lead and ensure that sessions are booked on time and alternatives are taken if need be. Mentees are expected let their managers know of their whereabouts during the period where they would be job shadowing or attending masterclasses Kindly sign the NDA and the Agreement attached to the email and send back to me ( Agreement needs your mentor to sign as well so you can get that back to me once you have your introduction session.) Please use the Development Plan to keep track of all the activities and learning you will be doing with your mentor. | D28: Career Mentor | E28: Full Time Employee | F28: Indian (South Africa) | G28: Female | H28: 40 - 49 | I28: FNB Retail COO (Tara Cabion) | J28: South Africa | K28: FNB | L28: 69000006171 FNB Retail Enterprise Project Management Office | M28: Programme Manager | N28: 6 - 10 Years | O28: Programme and Project Management | P28: 4860098 | Q28: Stephanie Bezuidenhout | R28: Full Time Employee | S28: Coloured (South Africa) | T28: Female | U28: 30 - 39 | V28: REMS Real Estate Management Services (Hanifah Khan) | W28: South Africa | X28: FNB | Y28: 22300008588 REMS Property | Z28: Property Administrator | AA28: 11 -15 Years | AB28: Administration | AC28: Create Mentorship Event for Stephanie Bezuidenhout with Shantal Reddy | AD28: 45156 | AE28: 45351
A29: 5266106 | B29: Alison Felix-Lodewyk | C29: Career guidance Manage a career transition. Better integration into a team/business unit | D29: Career Mentor | E29: Full Time Employee | F29: Coloured (South Africa) | G29: Female | H29: 50 - 59 | I29: FNB Personal Human Capital (Shalini John) | J29: South Africa | K29: FNB | L29: 84900003961 FNB ConnectMe EXCO | M29: Human Capital Manager | N29: 6 - 10 Years | O29: Business Human Capital | P29: 5183855 | Q29: Chizoba Mkhwanazi | R29: Full Time Employee | S29: African (South Africa) | T29: Female | U29: 20 - 29 | V29: DirectAxis (Adiela April) | W29: South Africa | X29: FNB | Y29: 99700015134 DA IT Development | Z29: Test Analyst | AA29: 6 - 10 Years | AB29: IT Testing | AC29: Create Mentorship Event for Chizoba Mkhwanazi with Alison Felix-Lodewyk | AD29: 44971 | AE29: 45639
A30: 2285681 | B30: Eddie Roodt | D30: Transition Mentor | E30: Full Time Employee | F30: White (South Africa) | G30: Male | H30: 50 - 59 | I30: FNB International SA (Tsholofelo Mosito) | J30: South Africa | K30: FNB | L30: 83200009889 FNB International SA Learning and Development | M30: Learning Consultant | N30: >20 Years | O30: Experience Architecting | P30: 5516307 | Q30: Mahlori Chauke (Terminated) | S30: African (South Africa) | T30: Male | U30: 30 - 39 | W30: South Africa | AA30: 1 Year | AC30: Create Mentorship Event for Mahlori Chauke (Terminated) with Eddie Roodt | AD30: 44855
A31: 5467845 | B31: Emmanuel Tsiame (Terminated) | D31: Career Mentor | F31: African (South Africa) | G31: Male | H31: 30 - 39 | J31: South Africa | N31: 2 Years | P31: 5573874 | Q31: Refilwe Leburu | R31: Full Time Employee | S31: African (South Africa) | T31: Female | U31: 30 - 39 | V31: FNB Private Banking and Advisory (Caswill Koert) | W31: South Africa | X31: FNB | Y31: 34100007232 PB&A Service Suite Advisor Engagement | Z31: Private Service Advisor | AA31: 3 - 5 Years | AB31: Client Relationship Management | AC31: Create Mentorship Event for Refilwe Leburu with Emmanuel Tsiame (Terminated) | AD31: 45063
A32: 2053527 | B32: Adnaan Rayned | D32: Career Mentor | E32: Full Time Employee | F32: Coloured (South Africa) | G32: Male | H32: 50 - 59 | I32: FNB Commercial Sales Cape (Stephan Claassen) | J32: South Africa | K32: FNB | L32: 34300005001 FNB Commercial Growth Cape Head Office | M32: Regional Head | N32: >20 Years | O32: Sales Management | P32: 5114713 | Q32: Yusuf Ahmed | R32: Full Time Employee | S32: Indian (South Africa) | T32: Male | U32: 30 - 39 | V32: FNB Commercial Projects and Operations (Gavilan Barnes) | W32: South Africa | X32: FNB | Y32: 34200005337 FNB Commercial Security Access Management | Z32: Information Security Administrator | AA32: 1 Year | AB32: IT Security | AC32: Create Mentorship Event for Yusuf Ahmed with Adnaan Rayned | AD32: 45264
A33: 5478960 | B33: Henry Lesar | D33: Career Mentor | E33: Full Time Employee | F33: Coloured (South Africa) | G33: Male | H33: 40 - 49 | I33: CDO Kernel Customer IT (Craig Coombs) | J33: South Africa | K33: FNB | L33: 79000005746 CDO Kernel CIS | M33: Application Development Manager | N33: 3 - 5 Years | O33: IT Development | P33: 5498783 | Q33: Thaveshni Govender | R33: Full Time Employee | S33: Indian (South Africa) | T33: Female | U33: 30 - 39 | V33: CDO Kernel iNterfaceX (Chris Bolle) | W33: South Africa | X33: FNB | Y33: 21800001994 CDO Kernel iNterfaceX Tech App and Mobile Dev App | Z33: Developer | AA33: 3 - 5 Years | AB33: IT Development | AC33: Create Mentorship Event for Thaveshni Govender with Henry Lesar | AD33: 44986
A34: 2404028 | B34: Debbie Maloney | C34: Growth and guidance | D34: Career Mentor | E34: Full Time Employee | F34: White (South Africa) | G34: Female | H34: 50 - 59 | I34: FNB Points of Presence (Edmar Topkin) | J34: South Africa | K34: FNB | L34: 771027100 FNB POP Branch Delivery Koffiefontein | M34: Associate | N34: >20 Years | O34: Client Relationship Management | P34: 4793854 | Q34: Makoae Lawrence Mothibe (Terminated) | S34: African (Lesotho) | T34: Male | U34: 50 - 59 | W34: Lesotho | AA34: 6 - 10 Years | AC34: Create Mentorship Event for Makoae Lawrence Mothibe (Terminated) with Debbie Maloney | AD34: 45260 | AE34: 45535
A35: 2010879 | B35: Dave Aitken (Terminated) | D35: Career Mentor | F35: White (South Africa) | G35: Male | H35: 50 - 59 | J35: South Africa | N35: >20 Years | P35: 2627388 | Q35: Fred Du Plessis | R35: Full Time Employee | S35: White (South Africa) | T35: Male | U35: 40 - 49 | V35: FNB Commercial Sales Gauteng North (Andile Ncoyini) | W35: South Africa | X35: FNB | Y35: 34200006503 FNB Commercial Sales Gauteng Midrand 10 to 60M | Z35: Sales Head | AA35: >20 Years | AB35: Direct Sales | AC35: Create Mentorship Event for Fred Du Plessis with Dave Aitken (Terminated) | AD35: 45108 | AE35: 45473
A36: 4610016 | B36: Gareth Kin | C36: Gareth is assisting Ayanda with Career Development | D36: Career Mentor | E36: Full Time Employee | F36: Coloured (South Africa) | G36: Male | H36: 40 - 49 | I36: FNB Private Segment (Philani Phakamani Potwana) | J36: South Africa | K36: FNB | L36: 41200007842 FNB Private Core Banking Exco | M36: Product Head | N36: 16 - 20 Years | O36: Product Management | P36: 5522633 | Q36: Ayanda Dubazana | R36: Full Time Employee | S36: African (South Africa) | T36: Female | U36: 30 - 39 | V36: FNB Retail Marketing (Sifiso Mahlangu) | W36: South Africa | X36: FNB | Y36: 85500006598 FNB Retail Marketing | Z36: Marketing Portfolio Manager | AA36: 3 - 5 Years | AB36: Marketing, Advertising and Media (incl. digital) | AC36: Create Mentorship Event for Ayanda Dubazana with Gareth Kin | AD36: 45108 | AE36: 45474
A37: 4792718 | B37: Grant Ravno (Terminated) | D37: Technical Mentor | F37: White (South Africa) | G37: Male | H37: 30 - 39 | J37: South Africa | N37: 11 -15 Years | P37: 4765745 | Q37: Tsholofelo Kgwele (Terminated) | S37: African (South Africa) | T37: Male | U37: 30 - 39 | W37: South Africa | AA37: 11 -15 Years | AC37: Create Mentorship Event for Tsholofelo Kgwele (Terminated) with Grant Ravno (Terminated) | AD37: 45231 | AE37: 45443
A38: 3486850 | B38: Ilyas Patel | C38: Shahida is looking for exposure in total reward | D38: Career Mentor | E38: Full Time Employee | F38: Indian (South Africa) | G38: Male | H38: 40 - 49 | I38: Group Human Capital (Zama Lamla) | J38: South Africa | K38: FirstRand Corporate Centre | L38: 20200003706 Group Reward | M38: Reward Head FCC and Group Shares | N38: 16 - 20 Years | O38: Experience Architecting | P38: 3614263 | Q38: Shahida Begg | R38: Full Time Employee | S38: Coloured (South Africa) | T38: Female | U38: 30 - 39 | V38: FNB Points of Presence (Charlene Calleja) | W38: South Africa | X38: FNB | Y38: 7710644300 FNB POP HC Operations and Talent Management | Z38: Operations Manager | AA38: 11 -15 Years | AB38: Operations | AC38: Create Mentorship Event for Shahida Begg with Ilyas Patel Edit Mentorship Event for Shahida Begg with Ilyas Patel | AD38: 45244 | AE38: 45596
A39: 3355268 | B39: Josh Minyuku (Terminated) | C39: Leadership in Branch programme | D39: Leadership Mentor | F39: African (South Africa) | G39: Male | H39: 40 - 49 | J39: South Africa | N39: 16 - 20 Years | P39: 4788540 | Q39: Kgaugelo Kulube | R39: Full Time Employee | S39: African (South Africa) | T39: Female | U39: 30 - 39 | V39: FNB Points of Presence (Abednigo Chauke) | W39: South Africa | X39: FNB | Y39: 7710693500 FNB POP Branch Delivery Zebediela Plaza | Z39: Branch Controller | AA39: 11 -15 Years | AB39: Administration | AC39: Create Mentorship Event for Kgaugelo Kulube with Josh Minyuku (Terminated) | AD39: 45209 | AE39: 45412
A40: 5235049 | B40: Rialivhuwa Mudau | C40: The purpose of the mentorship is to Learn about different careers and fields. Provide guidance and support during difficult times, and in narrowing what to study to archive my career goals. Clarify and narrow down my unique strengths and journey | D40: Career Mentor | E40: Full Time Employee | F40: African (South Africa) | G40: Female | H40: 30 - 39 | I40: FNB Personal Segment Advisory and Suites (Devesh Naidoo) | J40: South Africa | K40: FNB | L40: 97200005382 PSAS Stratco | M40: Risk Head | N40: 6 - 10 Years | O40: Operational Risk | P40: 5246628 | Q40: Anelisa Singanzi | R40: Full Time Employee | S40: African (South Africa) | T40: Female | U40: 40 - 49 | V40: FNB Loans (Prolene Louw) | W40: South Africa | X40: FNB | Y40: 79100003305 FNB Consumer Loans Internal Collections | Z40: Collections Advisor | AA40: 11 -15 Years | AB40: Collections and Recoveries | AC40: Create Mentorship Event for Anelisa Singanzi with Rialivhuwa Mudau | AD40: 44593 | AE40: 45833
A41: 3054829 | B41: Crystal Brown | C41: The 12th of December will mark my first year again since re-joining the Bank. I will identify gaps in Leadership development and enroll where applicable, job shadow and skills development. | D41: Leadership Mentor | E41: PHI Benefit | F41: Coloured (South Africa) | G41: Female | H41: 40 - 49 | I41: FNB Commercial Sales Cape (Philip Poole) | J41: South Africa | K41: FNB | L41: 34200009138 FNB Commercial Agriculture Western Cape | M41: Relationship Analyst | N41: >20 Years | O41: Client Relationship Management | P41: 3054241 | Q41: Laetitia Kay | R41: Full Time Employee | S41: Coloured (South Africa) | T41: Female | U41: 40 - 49 | V41: FNB Points of Presence (Clinton Barthus) | W41: South Africa | X41: FNB | Y41: 771038000 FNB POP Branch Delivery Strand | Z41: Branch Delivery Sales and Service Team Leader | AA41: 3 - 5 Years | AB41: Direct Sales | AC41: Create Mentorship Event for Laetitia Kay with Crystal Brown | AD41: 45247 | AE41: 45291
A42: 4873033 | B42: Collen Tshebo | D42: Leadership Mentor | E42: Full Time Employee | G42: Male | H42: 30 - 39 | I42: FNB Botswana Business Support WesBank (Goeme Ganetsang) | J42: Botswana | K42: FNB | L42: 5010394500 FNB Botswana Business Support | M42: Client Portfolio Analyst | N42: 6 - 10 Years | O42: Client Services Support and Delivery | P42: 5599199 | Q42: Thuto Kofi (Terminated) | T42: Female | U42: 20 - 29 | W42: Botswana | AA42: <1 Year | AC42: Create Mentorship Event for Thuto Kofi (Terminated) with Collen Tshebo | AD42: 45139 | AE42: 45505
A43: 4617444 | B43: Riana Prins | D43: Career Mentor | E43: Full Time Employee | F43: White (South Africa) | G43: Female | H43: 50 - 59 | I43: FNB Commercial National Sales and Service (Jurgens Boshoff) | J43: South Africa | K43: FNB | L43: 34300007707 FNB Financial Advisory Business Central | M43: Financial Advisory Channel Head | N43: 16 - 20 Years | O43: Investor Services | P43: 5128218 | Q43: Waldo Visagie | R43: Commission With Fixed Pay | S43: White (South Africa) | T43: Male | U43: 40 - 49 | V43: FNB Commercial National Sales and Service (Riana Prins) | W43: South Africa | X43: FNB | Y43: 34300004503 FNB Financial Advisory Business Western Cape | Z43: Business Financial Advisor | AA43: 6 - 10 Years | AB43: Investor Services | AC43: Create Mentorship Event for Waldo Visagie with Riana Prins | AD43: 45292 | AE43: 45657
A44: 2746573 | B44: Himal Parbhoo | D44: Career Mentor | E44: Full Time Employee | F44: Indian (South Africa) | G44: Male | H44: 40 - 49 | I44: FNB Private Segment (Sizwe Nxedlana) | J44: South Africa | K44: FNB | L44: 85500008551 FNB Retail Exco | M44: Chief Executive Officer Cash Investments Retail | N44: 16 - 20 Years | O44: Operations | P44: 5320763 | Q44: Balesh Raniga | R44: Full Time Employee | S44: Indian (South Africa) | T44: Male | U44: 30 - 39 | V44: FNB Private Core Banking (Daryl Rajah) | W44: South Africa | X44: FNB | Y44: 41200003615 FNB Private Core Banking Private Clients | Z44: Product Portfolio Manager | AA44: 3 - 5 Years | AB44: Product Management | AC44: Create Mentorship Event for Balesh Raniga with Himal Parbhoo | AD44: 45266 | AE44: 45631
A45: 3818748 | B45: Hlamalani Mashaba | D45: Leadership Mentor | E45: Full Time Employee | F45: African (South Africa) | G45: Male | H45: 40 - 49 | I45: FNB Chief Finance Office iFinance (Parmasivan Pillay) | J45: South Africa | K45: FirstRand Corporate Centre | L45: 20200011041 FRCC Group Project Management Office | M45: Capability Lead | N45: 11 -15 Years | O45: Operations | P45: 5256984 | Q45: Thomas Tonga | R45: Full Time Employee | S45: African (South Africa) | T45: Male | U45: 30 - 39 | V45: FNB Chief Risk Office IT (Paul Hazelton) | W45: South Africa | X45: FNB | Y45: 39400008197 FNB Chief Risk Office IT | Z45: Platform Service Owner | AA45: 6 - 10 Years | AB45: System Design and Administration | AC45: Create Mentorship Event for Thomas Tonga with Hlamalani Mashaba | AD45: 45244
A46: 5004608 | B46: Maleseli Lorraine Chefa | D46: Leadership Mentor | E46: Full Time Employee | F46: African (Lesotho) | G46: Female | H46: 30 - 39 | I46: FNB Lesotho (Daniel Mohau) | J46: Lesotho | K46: FNB | L46: 51800001852 FNB Lesotho OPC | M46: Team Leader Back Office | N46: 6 - 10 Years | O46: Operations | P46: 5365732 | Q46: Ikaneng Francina Setlhotlelo | R46: Full Time Employee | T46: Female | U46: 20 - 29 | V46: FNB Lesotho (Mamello Selomo) | W46: Lesotho | X46: FNB | Y46: 51800008847 FNBL Finance | Z46: Procurement Coordinator | AA46: 3 - 5 Years | AB46: Procurement and Supply Chain Management | AC46: Close Mentorship Event for Ikaneng Francina Setlhotlelo with Maleseli Lorraine Chefa Create Mentorship Event for Ikaneng Francina Setlhotlelo with Maleseli Lorraine Chefa | AD46: 45139 | AE46: 45443 | AF46: Mentoring Needs Fulfilled
A47: 5087112 | B47: Betty Moabelo | C47: I SEEK TO BE TAKEN THROUGH ON THE MERCHANT JOUNEY ON THE FULFILMENT ASPECTS AS I LOOK AT JOINING THE MERCHANT SERVICE TEAM IN THE NEAR FUTURE. | D47: Technical Mentor | E47: Full Time Employee | F47: African (South Africa) | G47: Female | H47: 40 - 49 | I47: FNB Commercial Merchant Services (Netsai Ngidi) | J47: South Africa | K47: FNB | L47: 22800004061 FNB Commercial Merchant Services Product and Solutions | M47: Industry Manager | N47: 6 - 10 Years | O47: Client Relationship Management | P47: 4632893 | Q47: Chipande Shisala | R47: Full Time Employee | T47: Male | U47: 30 - 39 | V47: FNB Zambia Operations (Mubukwanu Mutiti (Inherited)) | W47: Zambia | X47: FNB | Y47: 55300003086 FNB Zambia Operations | Z47: Administration Assistant | AA47: 11 -15 Years | AB47: Administration | AC47: Create Mentorship Event for Chipande Shisala with Betty Moabelo | AD47: 45294 | AE47: 45310
A48: 7538677 | B48: Carol Dlamini (Terminated) | C48: I’m seeing myself as a branch administrator for the bank . I also want to broaden my knowledge and experience in the banking world. My future is in the financial sector and I want to learn more about the banking system and development myself gradually to make a difference in FNB. I believe it is my time to show my skills, knowledge and passion for the brand. | D48: Career Mentor | F48: African (South Africa) | G48: Female | H48: 30 - 39 | J48: South Africa | N48: 16 - 20 Years | P48: 3426416 | Q48: Mandla Mathipa | R48: OBR With Fixed Pay | S48: African (South Africa) | T48: Male | U48: 30 - 39 | V48: FNB Points of Presence (Xolani Nkosi) | W48: South Africa | X48: FNB | Y48: 7710115300 FNB POP Branch Delivery Village Horizon | Z48: Branch Advisor FAIS | AA48: 16 - 20 Years | AB48: Client Services Support and Delivery | AC48: Close Mentorship Event for Mandla Mathipa with Carol Dlamini (Terminated) Create Mentorship Event for Mandla Mathipa with Carol Dlamini (Terminated) | AD48: 45257 | AE48: 45656 | AF48: Mentor Withdrawal - Availability
A49: 1989413 | B49: Marlene Van Nel (Terminated) | C49: To improve my leadership skills and groom me for future management positions. | D49: Leadership Mentor | F49: Coloured (South Africa) | G49: Female | H49: 60 - 64 | J49: South Africa | N49: 11 -15 Years | P49: 2475960 | Q49: Igna Kirsten | R49: Full Time Employee | S49: White (South Africa) | T49: Female | U49: 50 - 59 | V49: FNB Points of Presence (Reece Brown) | W49: South Africa | X49: FNB | Y49: 771027700 FNB POP Branch Delivery Kuruman | Z49: Local Market Operations Manager | AA49: >20 Years | AB49: Administration | AC49: Create Mentorship Event for Igna Kirsten with Marlene Van Nel (Terminated) | AD49: 45258 | AE49: 45624
A50: 4878922 | B50: Fridah Maake-Gumede | D50: Career Mentor | E50: Full Time Employee | F50: African (South Africa) | G50: Female | H50: 30 - 39 | I50: FNB Points of Presence (Angela Nathoo) | J50: South Africa | K50: FNB | L50: 7710179200 FNB POP Branch Delivery Middelburg Mall | M50: Local Market Manager | N50: 6 - 10 Years | O50: Client Relationship Management | P50: 4912233 | Q50: Maltilda Sonopo | R50: OBR With Fixed Pay | S50: African (South Africa) | T50: Female | U50: 30 - 39 | V50: FNB Points of Presence (Mothibedi Moaludi) | W50: South Africa | X50: FNB | Y50: 771013700 FNB POP Branch Delivery Nigel | Z50: Branch Advisor FAIS | AA50: 3 - 5 Years | AB50: Client Services Support and Delivery | AC50: Create Mentorship Event for Maltilda Sonopo with Fridah Maake-Gumede | AD50: 45253 | AE50: 45412
A51: 4633369 | B51: Chipo Mwenya | D51: Career Mentor | E51: Full Time Employee | G51: Female | H51: 30 - 39 | I51: FNB Zambia Retail Segment (Jeremiah Namitondo) | J51: Zambia | K51: FNB | L51: 55300009179 FNB Zambia Choma Branch | M51: Branch Manager | N51: 11 -15 Years | O51: Client Experience and Value Management | P51: 4931181 | Q51: Eugine Hatyoka | R51: Full Time Employee | T51: Male | U51: 30 - 39 | V51: FNB Zambia Retail Segment (Jason Silwamba) | W51: Zambia | X51: FNB | Y51: 55300001894 FNB Zambia Kabwe Branch | Z51: Branch Administrator | AA51: 6 - 10 Years | AB51: Administration | AC51: Create Mentorship Event for Eugine Hatyoka with Chipo Mwenya | AD51: 45257 | AE51: 45657
A52: 4535286 | B52: Athena Botha | D52: Transition Mentor | E52: Full Time Employee | F52: White (South Africa) | G52: Female | H52: 50 - 59 | I52: FNB Commercial Analytics Insights Data (Patrick Motshweni) | J52: South Africa | K52: FNB | L52: 34300005518 FNB Commercial Data Office | M52: Information Architect Head | N52: 11 -15 Years | O52: Data Management, Maintenance and Security | P52: 3678482 | Q52: Jermaine Varnicker | R52: Full Time Employee | S52: Coloured (South Africa) | T52: Male | U52: 30 - 39 | V52: FNB Commercial Cash (Andries Vermaak) | W52: South Africa | X52: FNB | Y52: 25200006132 FNB Commercial IT Application Development Cash | Z52: Data Analyst | AA52: 11 -15 Years | AB52: Data Management, Maintenance and Security | AC52: Create Mentorship Event for Jermaine Varnicker with Athena Botha | AD52: 44888
A53: 2860538 | B53: Lou-Ann Oosthuizen | C53: To empower and provide On the job training | D53: Leadership Mentor | E53: Full Time Employee | F53: White (South Africa) | G53: Female | H53: 40 - 49 | I53: FNB Points of Presence (Hein Hoffman) | J53: South Africa | K53: FNB | L53: 771044800 FNB POP Branch Delivery Hyde Park | M53: Branch Administrator | N53: >20 Years | O53: Administration | P53: 3719138 | Q53: Caroline Nkuna | R53: Full Time Employee | S53: African (South Africa) | T53: Female | U53: 30 - 39 | V53: FNB Points of Presence (Kobus Steenkamp) | W53: South Africa | X53: FNB | Y53: 771042500 FNB POP Branch Delivery Wepener | Z53: Associate | AA53: 11 -15 Years | AB53: Client Relationship Management | AC53: Create Mentorship Event for Caroline Nkuna with Lou-Ann Oosthuizen | AD53: 45293 | AE53: 45626
A54: 4878922 | B54: Fridah Maake-Gumede | C54: Leadership | D54: Leadership Mentor | E54: Full Time Employee | F54: African (South Africa) | G54: Female | H54: 30 - 39 | I54: FNB Points of Presence (Angela Nathoo) | J54: South Africa | K54: FNB | L54: 7710179200 FNB POP Branch Delivery Middelburg Mall | M54: Local Market Manager | N54: 6 - 10 Years | O54: Client Relationship Management | P54: 4912233 | Q54: Maltilda Sonopo | R54: OBR With Fixed Pay | S54: African (South Africa) | T54: Female | U54: 30 - 39 | V54: FNB Points of Presence (Mothibedi Moaludi) | W54: South Africa | X54: FNB | Y54: 771013700 FNB POP Branch Delivery Nigel | Z54: Branch Advisor FAIS | AA54: 3 - 5 Years | AB54: Client Services Support and Delivery | AC54: Create Mentorship Event for Maltilda Sonopo with Fridah Maake-Gumede | AD54: 45253 | AE54: 45412
A55: 3384292 | B55: Annastasia Williams | D55: Leadership Mentor | E55: Full Time Employee | F55: Racially disadvantaged (Namibia) | G55: Female | H55: 50 - 59 | I55: FNB Namibia Limited (Wiann Mans) | J55: Namibia | K55: FNB | L55: 302031B9D555 FNB Namibia Human Capital | M55: Learning and Development Manager | N55: 11 -15 Years | O55: Experience Architecting | P55: 3388115 | Q55: Beata Kalola | R55: Full Time Employee | S55: Racially disadvantaged (Namibia) | T55: Female | U55: 30 - 39 | V55: FNB Namibia Limited (Margareth Dawid) | W55: Namibia | X55: FNB | Y55: 302000001454 FNB Namibia Commercial Clusters | Z55: Relationship Analyst Clusters | AA55: 11 -15 Years | AB55: Client Relationship Management | AC55: Create Mentorship Event for Beata Kalola with Annastasia Williams | AD55: 45252 | AE55: 45473
A56: 3377326 | B56: Yamillah Katjirua | C56: as agreed between Yamilla and Prudence, this mentorship is to assist Prudence in developing herself and growing her care | D56: Career Mentor | E56: Full Time Employee | F56: Racially disadvantaged (Namibia) | G56: Female | H56: 50 - 59 | I56: FNB Namibia Limited (Emmanuel Murwira) | J56: Namibia | K56: FNB | L56: 846000004213 Ashburton Investment Managers (Pty) Ltd | M56: Compliance Head | N56: 6 - 10 Years | O56: Compliance | P56: 5071429 | Q56: Prudence Motha (Terminated) | S56: African (South Africa) | T56: Female | U56: 30 - 39 | W56: South Africa | AA56: 6 - 10 Years | AC56: Create Mentorship Event for Prudence Motha (Terminated) with Yamillah Katjirua | AD56: 45254 | AE56: 45618
A57: 3252396 | B57: Diran Gajoo | D57: Career Mentor | E57: Full Time Employee | F57: Indian (South Africa) | G57: Male | H57: 40 - 49 | I57: FNB Chief Risk Office Executive (Brandon Olivier) | J57: South Africa | K57: FNB | L57: 39400004555 FNB Chief Risk Office Screening Services COO | M57: Operations Head | N57: 11 -15 Years | O57: Operations | P57: 5463130 | Q57: Nish Chinappa | R57: Full Time Employee | S57: Indian (South Africa) | T57: Male | U57: 40 - 49 | V57: FNB Private Core Banking (Nico Oosthuizen) | W57: South Africa | X57: FNB | Y57: 41200003546 FNB Private Core Banking Operations Support | Z57: Business Intelligence Analyst | AA57: 3 - 5 Years | AB57: Business Intelligence | AC57: Create Mentorship Event for Nish Chinappa with Diran Gajoo | AD57: 45139 | AE57: 45473
A58: 2627388 | B58: Fred Du Plessis | C58: To be guided on how to maneuver through the transition of the coporate world to be a better leader and more equiped with skills and knowledge | D58: Transition Mentor | E58: Full Time Employee | F58: White (South Africa) | G58: Male | H58: 40 - 49 | I58: FNB Commercial Sales Gauteng North (Andile Ncoyini) | J58: South Africa | K58: FNB | L58: 34200006503 FNB Commercial Sales Gauteng Midrand 10 to 60M | M58: Sales Head | N58: >20 Years | O58: Direct Sales | P58: 4856945 | Q58: Lucky Phiri | R58: OBR With Fixed Pay | S58: African (South Africa) | T58: Male | U58: 30 - 39 | V58: FNB Points of Presence (Innocent Radebe) | W58: South Africa | X58: FNB | Y58: 7710841400 FNB POP External Sales Local Market | Z58: External Sales and Service Advisor Lead OBR | AA58: 6 - 10 Years | AB58: Direct Sales | AC58: Create Mentorship Event for Lucky Phiri with Fred Du Plessis | AD58: 45307 | AE58: 45639
A59: 3377326 | B59: Yamillah Katjirua | D59: Career Mentor | E59: Full Time Employee | F59: Racially disadvantaged (Namibia) | G59: Female | H59: 50 - 59 | I59: FNB Namibia Limited (Emmanuel Murwira) | J59: Namibia | K59: FNB | L59: 846000004213 Ashburton Investment Managers (Pty) Ltd | M59: Compliance Head | N59: 6 - 10 Years | O59: Compliance | P59: 4696549 | Q59: Fortune Boois-Mafwila | R59: Full Time Employee | S59: Racially disadvantaged (Namibia) | T59: Female | U59: 40 - 49 | V59: FNB Namibia Limited (Sandi Isaacs) | W59: Namibia | X59: FNB | Y59: 302000006866 FNB Namibia Compliance | Z59: Financial Crime Operations Manager | AA59: 11 -15 Years | AB59: Fraud Risk | AC59: Create Mentorship Event for Fortune Boois-Mafwila with Yamillah Katjirua | AD59: 45565
A60: 3803821 | B60: Sabata Chomane | D60: Leadership Mentor | E60: Full Time Employee | F60: African (South Africa) | G60: Male | H60: 40 - 49 | I60: FNB Points of Presence (Kobus Steenkamp) | J60: South Africa | K60: FNB | L60: 771028000 FNB POP Branch Delivery Ladybrand | M60: Associate | N60: 11 -15 Years | O60: Client Relationship Management | P60: 3716333 | Q60: Mohlekaze Hlubi | R60: OBR With Fixed Pay | S60: African (South Africa) | T60: Female | U60: 30 - 39 | V60: FNB Points of Presence (Lee Ainslie) | W60: South Africa | X60: FNB | Y60: 771032600 FNB POP Branch Delivery Parys | Z60: Branch Advisor FAIS | AA60: 6 - 10 Years | AB60: Client Services Support and Delivery | AC60: Create Mentorship Event for Mohlekaze Hlubi with Sabata Chomane | AD60: 45307 | AE60: 45650
A61: 7527403 | B61: Daren Moodley (Terminated) | C61: Contract 2024 | D61: Career Mentor | F61: Indian (South Africa) | G61: Male | H61: 30 - 39 | J61: South Africa | N61: 11 -15 Years | P61: 3253759 | Q61: Vikash Mahabally | R61: Full Time Employee | S61: Indian (South Africa) | T61: Male | U61: 40 - 49 | V61: FNB Points of Presence (Musa Vukeya) | W61: South Africa | X61: FNB | Y61: 7710405800 FNB POP Commercial Collaboration | Z61: Key Accounts Manager | AA61: 16 - 20 Years | AB61: Client Relationship Management | AC61: Create Mentorship Event for Vikash Mahabally with Daren Moodley (Terminated) | AD61: 45266 | AE61: 45266
A62: 3902161 | B62: Mariska Walkerley | C62: To guide and monitor success. | D62: Workplace Buddy | E62: Full Time Employee | F62: White (South Africa) | G62: Female | H62: 50 - 59 | I62: FNB Wealth and Investments (Malebo Selepe) | J62: South Africa | K62: FNB | L62: 46700006629 FNB WI IT Dev | M62: Applications Developer | N62: 11 -15 Years | O62: IT Development | P62: 4921151 | Q62: Nokwazi Mabaso | R62: OBR With Fixed Pay | S62: African (South Africa) | T62: Female | U62: 30 - 39 | V62: FNB Points of Presence (Nomfundo Favourite Chili) | W62: South Africa | X62: FNB | Y62: 771007900 FNB POP Branch Delivery Durban North | Z62: Branch Advisor FAIS | AA62: 6 - 10 Years | AB62: Client Services Support and Delivery | AC62: Create Mentorship Event for Nokwazi Mabaso with Mariska Walkerley | AD62: 45234
A63: 4878922 | B63: Fridah Maake-Gumede | D63: Career Mentor | E63: Full Time Employee | F63: African (South Africa) | G63: Female | H63: 30 - 39 | I63: FNB Points of Presence (Angela Nathoo) | J63: South Africa | K63: FNB | L63: 7710179200 FNB POP Branch Delivery Middelburg Mall | M63: Local Market Manager | N63: 6 - 10 Years | O63: Client Relationship Management | P63: 4654641 | Q63: Kgotlelelo Makeke (Terminated) | S63: African (South Africa) | T63: Male | U63: 30 - 39 | W63: South Africa | AA63: 1 Year | AC63: Create Mentorship Event for Kgotlelelo Makeke (Terminated) with Fridah Maake-Gumede | AD63: 45323 | AE63: 45351
A64: 4878922 | B64: Fridah Maake-Gumede | D64: Leadership Mentor | E64: Full Time Employee | F64: African (South Africa) | G64: Female | H64: 30 - 39 | I64: FNB Points of Presence (Angela Nathoo) | J64: South Africa | K64: FNB | L64: 7710179200 FNB POP Branch Delivery Middelburg Mall | M64: Local Market Manager | N64: 6 - 10 Years | O64: Client Relationship Management | P64: 3837157 | Q64: Sibongile Dhlamini | R64: OBR With Fixed Pay | S64: African (South Africa) | T64: Female | U64: 40 - 49 | V64: FNB Points of Presence (Reuben Diphoko) | W64: South Africa | X64: FNB | Y64: 771037200 FNB POP Branch Delivery Standerton | Z64: Branch Advisor FAIS | AA64: 11 -15 Years | AB64: Client Services Support and Delivery | AC64: Create Mentorship Event for Sibongile Dhlamini with Fridah Maake-Gumede | AD64: 45323 | AE64: 45413
A65: 4741617 | B65: Bina Rowjee | C65: I wanted a mentor to help me navigate my career as I am new in this corporate world | D65: Career Mentor | E65: Full Time Employee | F65: Indian (South Africa) | G65: Female | H65: 30 - 39 | I65: FNB Central Finance (Wesley Pretorius) | J65: South Africa | K65: FNB | L65: 39400004539 FNB Finance Data and analytics | M65: Business Intelligence Manager | N65: 11 -15 Years | O65: Business Intelligence | P65: 5605040 | Q65: Mbali Ohlson | R65: Full Time Employee | S65: African (South Africa) | T65: Female | U65: 20 - 29 | V65: FNB Retail CDAO (Jaysha Singh) | W65: South Africa | X65: FNB | Y65: 34100003373 PB&A BI & Data Analytics | Z65: Business Intelligence Analyst | AA65: 3 - 5 Years | AB65: Business Intelligence | AC65: Close Mentorship Event for Mbali Ohlson with Bina Rowjee Create Mentorship Event for Mbali Ohlson with Bina Rowjee | AD65: 45047 | AE65: 45299 | AF65: Mentor Withdrawal - Availability
A66: 3818748 | B66: Hlamalani Mashaba | D66: Leadership Mentor | E66: Full Time Employee | F66: African (South Africa) | G66: Male | H66: 40 - 49 | I66: FNB Chief Finance Office iFinance (Parmasivan Pillay) | J66: South Africa | K66: FirstRand Corporate Centre | L66: 20200011041 FRCC Group Project Management Office | M66: Capability Lead | N66: 11 -15 Years | O66: Operations | P66: 5455030 | Q66: Mologadi Monakhisi (Terminated) | S66: African (South Africa) | T66: Female | U66: 30 - 39 | W66: South Africa | AA66: 2 Years | AC66: Create Mentorship Event for Mologadi Monakhisi (Terminated) with Hlamalani Mashaba | AD66: 45078 | AE66: 45444
A67: 4805062 | B67: Zaheer Ismail | D67: Transition Mentor | E67: Full Time Employee | F67: Indian (South Africa) | G67: Male | H67: 30 - 39 | I67: Group Human Capital (Dudu Moloko) | J67: South Africa | K67: FirstRand Corporate Centre | L67: 20200007954 FRCC People Governance Learning Compliance | M67: Leadership Development Specialist | N67: 11 -15 Years | O67: Experience Architecting | P67: 4528204 | Q67: Yoshini Naidoo (Terminated) | S67: Indian (South Africa) | T67: Female | U67: 50 - 59 | W67: South Africa | AA67: 16 - 20 Years | AC67: Close Mentorship Event for Yoshini Naidoo (Terminated) with Zaheer Ismail Create Mentorship Event for Yoshini Naidoo (Terminated) with Zaheer Ismail | AD67: 45267 | AE67: 45281 | AF67: Mentee Withdrawal - Change in Mentoring Needs
A68: 7527403 | B68: Daren Moodley (Terminated) | C68: upskilling. | D68: Career Mentor | F68: Indian (South Africa) | G68: Male | H68: 30 - 39 | J68: South Africa | N68: 11 -15 Years | P68: 2421143 | Q68: Daya Govender | R68: Full Time Employee | S68: Indian (South Africa) | T68: Male | U68: 50 - 59 | V68: FNB Points of Presence (Musa Vukeya) | W68: South Africa | X68: FNB | Y68: 7710405800 FNB POP Commercial Collaboration | Z68: Key Accounts Manager | AA68: >20 Years | AB68: Client Relationship Management | AC68: Create Mentorship Event for Daya Govender with Daren Moodley (Terminated) | AD68: 45261 | AE68: 45412
A69: 4771281 | B69: Mitchell Ncube | C69: Career alignment and guidance | D69: Transition Mentor | E69: Full Time Employee | F69: African (South Africa) | G69: Female | H69: 40 - 49 | I69: FNB Personal Core Banking (Jolandi Jansen Van Vuuren) | J69: South Africa | K69: FNB | L69: 28100006605 RCB Risk Management Gauteng | M69: Credit Portfolio Management Head | N69: 11 -15 Years | O69: Credit Risk | P69: 4815793 | Q69: Sandra Mnyoni | R69: Full Time Employee | S69: African (South Africa) | T69: Female | U69: 30 - 39 | V69: FNB Personal Segment Advisory and Suites (Nicole Greeves) | W69: South Africa | X69: FNB | Y69: 97200010975 PSAS Case Management | Z69: Service and Sales Advisor | AA69: 11 -15 Years | AB69: Client Services Support and Delivery | AC69: Create Mentorship Event for Sandra Mnyoni with Mitchell Ncube | AD69: 44835 | AE69: 45230
A70: 7527403 | B70: Daren Moodley (Terminated) | C70: Overall achievement of Goals and Measures as set out in agreed Points of Presence Staffing Solutions Key Account Manager Overall achievement of Goals and Measures as set out in agreed Points of Presence Staffing Solutions Operations Manager Contract Overall achievement of Goals and Measures as set out in agreed Points of Presence Staffing Solutions Administrator Contract | D70: Leadership Mentor | F70: Indian (South Africa) | G70: Male | H70: 30 - 39 | J70: South Africa | N70: 11 -15 Years | P70: 3253759 | Q70: Vikash Mahabally | R70: Full Time Employee | S70: Indian (South Africa) | T70: Male | U70: 40 - 49 | V70: FNB Points of Presence (Musa Vukeya) | W70: South Africa | X70: FNB | Y70: 7710405800 FNB POP Commercial Collaboration | Z70: Key Accounts Manager | AA70: 16 - 20 Years | AB70: Client Relationship Management | AC70: Create Mentorship Event for Vikash Mahabally with Daren Moodley (Terminated) | AD70: 45266 | AE70: 45266
A71: 7527403 | B71: Daren Moodley (Terminated) | C71: Upskilling to gain experience so as to advance further in my career. | D71: Leadership Mentor | F71: Indian (South Africa) | G71: Male | H71: 30 - 39 | J71: South Africa | N71: 11 -15 Years | P71: 2421143 | Q71: Daya Govender | R71: Full Time Employee | S71: Indian (South Africa) | T71: Male | U71: 50 - 59 | V71: FNB Points of Presence (Musa Vukeya) | W71: South Africa | X71: FNB | Y71: 7710405800 FNB POP Commercial Collaboration | Z71: Key Accounts Manager | AA71: >20 Years | AB71: Client Relationship Management | AC71: Create Mentorship Event for Daya Govender with Daren Moodley (Terminated) | AD71: 45314 | AE71: 45471
A72: 3472892 | B72: Nozipho Duma | C72: Leadership, individual branding, career development | D72: Leadership Mentor | E72: Full Time Employee | F72: African (South Africa) | G72: Female | H72: 40 - 49 | I72: FNB Broader Africa (Bydon Longwe) | J72: South Africa | K72: FNB | L72: 83200009887 FNB International SA Exco | M72: Chief Data and Analytics Officer | N72: 6 - 10 Years | O72: Analytics | P72: 5098858 | Q72: Veronika Jacobsz | R72: Full Time Employee | S72: White (South Africa) | T72: Female | U72: 30 - 39 | V72: FNB Dynamic Decisioning Project Delivery (Cindy John) | W72: South Africa | X72: FNB | Y72: 23900006144 FNB Dynamic Decisioning Project Delivery | Z72: Project Management Office Portfolio Manager | AA72: 6 - 10 Years | AB72: Programme and Project Management | AC72: Close Mentorship Event for Veronika Jacobsz with Nozipho Duma Create Mentorship Event for Veronika Jacobsz with Nozipho Duma | AD72: 44578 | AE72: 44890 | AF72: Mentee Withdrawal - Availability
A73: 2423243 | B73: Bongi Tshabangu | D73: Leadership Mentor | E73: Full Time Employee | F73: African (South Africa) | G73: Female | H73: 50 - 59 | I73: FNB Points of Presence (Reuben Fernandez) | J73: South Africa | K73: FNB | L73: 7710237600 FNB POP Regional Office Mpumalanga | M73: Regional Operations Manager | N73: >20 Years | O73: Operations | P73: 5121159 | Q73: Naledi Modipane (Terminated) | S73: African (South Africa) | T73: Female | U73: 30 - 39 | W73: South Africa | AA73: 6 - 10 Years | AC73: Create Mentorship Event for Naledi Modipane (Terminated) with Bongi Tshabangu | AD73: 45293 | AE73: 45322
A74: 4878922 | B74: Fridah Maake-Gumede | D74: Career Mentor | E74: Full Time Employee | F74: African (South Africa) | G74: Female | H74: 30 - 39 | I74: FNB Points of Presence (Angela Nathoo) | J74: South Africa | K74: FNB | L74: 7710179200 FNB POP Branch Delivery Middelburg Mall | M74: Local Market Manager | N74: 6 - 10 Years | O74: Client Relationship Management | P74: 4838734 | Q74: Reuben Diphoko | R74: Full Time Employee | S74: African (South Africa) | T74: Male | U74: 30 - 39 | V74: FNB Points of Presence (Makarabo Mahlomotja) | W74: South Africa | X74: FNB | Y74: 771037200 FNB POP Branch Delivery Standerton | Z74: Branch Delivery Sales and Service Team Leader | AA74: 11 -15 Years | AB74: Direct Sales | AC74: Create Mentorship Event for Reuben Diphoko with Fridah Maake-Gumede | AD74: 45323 | AE74: 45382
A75: 4878922 | B75: Fridah Maake-Gumede | D75: Leadership Mentor | E75: Full Time Employee | F75: African (South Africa) | G75: Female | H75: 30 - 39 | I75: FNB Points of Presence (Angela Nathoo) | J75: South Africa | K75: FNB | L75: 7710179200 FNB POP Branch Delivery Middelburg Mall | M75: Local Market Manager | N75: 6 - 10 Years | O75: Client Relationship Management | P75: 4868463 | Q75: Makarabo Mahlomotja | R75: Full Time Employee | S75: African (South Africa) | T75: Female | U75: 40 - 49 | V75: FNB Points of Presence (Angela Nathoo) | W75: South Africa | X75: FNB | Y75: 771037200 FNB POP Branch Delivery Standerton | Z75: Associate | AA75: 11 -15 Years | AB75: Client Relationship Management | AC75: Create Mentorship Event for Makarabo Mahlomotja with Fridah Maake-Gumede | AD75: 45292 | AE75: 45535
A76: 7552793 | B76: Theo Ngoma | D76: Leadership Mentor | E76: Full Time Employee | F76: African (South Africa) | G76: Female | H76: 30 - 39 | I76: CDO Infrastructure and Security Services (Ntswaki Lecage) | J76: South Africa | K76: FNB | L76: 20700005266 CDO Infrastructure and Security Services Command Centre | M76: Enterprise Systems Manager | N76: 3 - 5 Years | O76: System Design and Administration | P76: 4692497 | Q76: Sihle Ncedani-Madlebe | R76: Full Time Employee | S76: African (South Africa) | T76: Female | U76: 30 - 39 | V76: FNB Points of Presence (Zukisa Gabela) | W76: South Africa | X76: FNB | Y76: 771034000 FNB POP Branch Delivery Port Alfred | Z76: Universal Advisor Lead | AA76: 11 -15 Years | AB76: Client Experience and Value Management | AC76: Create Mentorship Event for Sihle Ncedani-Madlebe with Theo Ngoma | AD76: 45269 | AE76: 45382
A77: 2746573 | B77: Himal Parbhoo | C77: Actuarial Science Mentoring Programme | D77: Z2-Programme Mentor (HC Managed) | E77: Full Time Employee | F77: Indian (South Africa) | G77: Male | H77: 40 - 49 | I77: FNB Private Segment (Sizwe Nxedlana) | J77: South Africa | K77: FNB | L77: 85500008551 FNB Retail Exco | M77: Chief Executive Officer Cash Investments Retail | N77: 16 - 20 Years | O77: Operations | P77: 5608627 | Q77: Neo Hlalele | R77: Full Time Employee | S77: African (South Africa) | T77: Female | U77: 20 - 29 | V77: FNB International SA Retail Credit (Drikus Conradie) | W77: South Africa | X77: FNB | Y77: 83200005888 FNB International SA Retail Credit | Z77: Data Scientist | AA77: 3 - 5 Years | AB77: Analytics | AC77: Create Mentorship Event for Neo Hlalele with Himal Parbhoo | AD77: 45139 | AE77: 45535
A78: 3477428 | B78: Shalati Ngobeni | D78: Leadership Mentor | E78: Full Time Employee | F78: African (South Africa) | G78: Female | H78: 40 - 49 | I78: FNB Points of Presence (Barry Kuhn) | J78: South Africa | K78: FNB | L78: 7710299500 FNB Points of Presence Sales and Collaboration | M78: Leadership Coach | N78: 16 - 20 Years | O78: Process and Business Analysis | P78: 7547463 | Q78: Stephana Tshehla | R78: Full Time Employee | S78: African (South Africa) | T78: Male | U78: 40 - 49 | V78: FNB Points of Presence (Sinah Mnisi) | W78: South Africa | X78: FNB | Y78: 7710248400 FNB POP Branch Delivery Centurion Mall | Z78: Branch Delivery Sales and Service Team Leader | AA78: 16 - 20 Years | AB78: Direct Sales | AC78: Create Mentorship Event for Stephana Tshehla with Shalati Ngobeni | AD78: 45272 | AE78: 45272
A79: 3082644 | B79: Pontsho Njoro | C79: The purpose of this mentorship is for me to acquire a skill set that will help me move and excel in the commercial space specifically commercial property finance and all other surrounding disciplines. | D79: Career Mentor | E79: Full Time Employee | F79: African (South Africa) | G79: Female | H79: 40 - 49 | I79: FNB Commercial Sales Inland (Regita Lawrence) | J79: South Africa | K79: FNB | L79: 34200006563 FNB Commercial Sales North West Enterprise | M79: Client Portfolio Executive | N79: 11 -15 Years | O79: Client Relationship Management | P79: 3862674 | Q79: Nomthandazo Rapodile | R79: Full Time Employee | S79: African (South Africa) | T79: Female | U79: 30 - 39 | V79: FNB Commercial Sales Inland (Kammie Coetzee) | W79: South Africa | X79: FNB | Y79: 34200006563 FNB Commercial Sales North West Enterprise | Z79: Client Portfolio Analyst | AA79: 11 -15 Years | AB79: Client Services Support and Delivery | AC79: Create Mentorship Event for Nomthandazo Rapodile with Pontsho Njoro | AD79: 45313 | AE79: 45471
A80: 7500262 | B80: Wilma Masilo | C80: BA | D80: Career Mentor | E80: Full Time Employee | F80: African (South Africa) | G80: Female | H80: 40 - 49 | I80: FNB Points of Presence (Bernice O Reilly) | J80: South Africa | K80: FNB | L80: 7710669900 FNB POP Branch Finance | M80: Regional Financial Manager | N80: 16 - 20 Years | O80: Financial Management | P80: 5110092 | Q80: Sibusiso Khumalo | R80: Full Time Employee | S80: African (South Africa) | T80: Male | U80: 30 - 39 | V80: FNB Points of Presence (Delisiwe Chilwane) | W80: South Africa | X80: FNB | Y80: 7710452300 FNB POP Nelspruit Crossing Centre | Z80: Universal Advisor Lead | AA80: 6 - 10 Years | AB80: Client Experience and Value Management | AC80: Create Mentorship Event for Sibusiso Khumalo with Wilma Masilo | AD80: 45272 | AE80: 45272
A81: 3773531 | B81: Louise Labuschagne | C81: Actuarial Science Mentoring Programme | D81: Z2-Programme Mentor (HC Managed) | E81: Full Time Employee | F81: White (South Africa) | G81: Female | H81: 30 - 39 | I81: FNB Commercial Cash Investments Chief Executive Office (Vaughan David) | J81: South Africa | K81: FNB | L81: 65100004404 FNB Premium Cash Investments Development | M81: Data Science Head | N81: 11 -15 Years | O81: Analytics | P81: 5617391 | Q81: Danika Ramalingum | R81: Full Time Employee | S81: Indian (South Africa) | T81: Female | U81: 20 - 29 | V81: Funding and Liquidity Management (Cameron Gough) | W81: South Africa | X81: FirstRand Corporate Centre | Y81: 78200000SFE Structured Finance | Z81: Group Treasury Structurer | AA81: 3 - 5 Years | AB81: Investment Banking | AC81: Create Mentorship Event for Danika Ramalingum with Louise Labuschagne | AD81: 45139 | AE81: 45535
A82: 3795446 | B82: Willem-Dirk Van'T Zand | C82: Actuarial Science Mentoring Programme | D82: Z2-Programme Mentor (HC Managed) | E82: Full Time Employee | F82: White (South Africa) | G82: Male | H82: 30 - 39 | I82: FCC Risk Management (Lindy Riphagen) | J82: South Africa | K82: FirstRand Corporate Centre | L82: 78200000FDD FCC Risk Management | M82: Risk Production and Modelling Head | N82: 11 -15 Years | O82: Asset Management | P82: 5611474 | Q82: Matthew Gerrish (Terminated) | S82: White (South Africa) | T82: Male | U82: 20 - 29 | W82: South Africa | AA82: 2 Years | AC82: Create Mentorship Event for Matthew Gerrish (Terminated) with Willem-Dirk Van'T Zand | AD82: 45139 | AE82: 45535
A83: 4762762 | B83: Shailesh Pillay | C83: Actuarial Science Mentoring Programme | D83: Z2-Programme Mentor (HC Managed) | E83: Full Time Employee | F83: Indian (South Africa) | G83: Male | H83: 40 - 49 | I83: FRCC ERM CRO Office (Mine Van Zyl) | J83: South Africa | K83: FirstRand Corporate Centre | L83: 20200008665 FRCC ERM Model Risk Management | M83: Model Risk Management Head | N83: 11 -15 Years | O83: Legal | P83: 5605911 | Q83: Salmaan Mukhtar (Terminated) | S83: Indian (South Africa) | T83: Male | U83: 20 - 29 | W83: South Africa | AA83: 2 Years | AC83: Create Mentorship Event for Salmaan Mukhtar (Terminated) with Shailesh Pillay | AD83: 45139 | AE83: 45535
A84: 5277264 | B84: Thabo Mahlaba | C84: For guidance on sales and service role | D84: Career Mentor | E84: OBR With Fixed Pay | F84: African (South Africa) | G84: Male | H84: 30 - 39 | I84: FNB Points of Presence (Nontobeko Kunene) | J84: South Africa | K84: FNB | L84: 771079400 FNB POP Branch Delivery Nelspruit Pinnacle | M84: Branch Advisor FAIS | N84: 6 - 10 Years | O84: Client Services Support and Delivery | P84: 5489091 | Q84: Mphumuzi Khoza | R84: OBR With Fixed Pay | S84: African (South Africa) | T84: Male | U84: 20 - 29 | V84: FNB Points of Presence (Nontobeko Kunene) | W84: South Africa | X84: FNB | Y84: 771079400 FNB POP Branch Delivery Nelspruit Pinnacle | Z84: Branch Advisor FAIS | AA84: 2 Years | AB84: Client Services Support and Delivery | AC84: Create Mentorship Event for Mphumuzi Khoza with Thabo Mahlaba | AD84: 45272 | AE84: 45455
A85: 3835057 | B85: Nhlamulo Thosi (Terminated) | D85: Technical Mentor | F85: African (South Africa) | G85: Male | H85: 30 - 39 | J85: South Africa | N85: 11 -15 Years | P85: 5300312 | Q85: Gift Rathekoane | R85: OBR With Fixed Pay | S85: African (South Africa) | T85: Male | U85: 30 - 39 | V85: FNB Points of Presence (Zinhle Mokoena) | W85: South Africa | X85: FNB | Y85: 7710248500 FNB POP Branch Delivery Diepkloof Square | Z85: Branch Advisor FAIS | AA85: 6 - 10 Years | AB85: Client Services Support and Delivery | AC85: Create Mentorship Event for Gift Rathekoane with Nhlamulo Thosi (Terminated) | AD85: 45273 | AE85: 45657
A86: 5156270 | B86: Kevin Myers | C86: Actuarial Science Mentoring Programme | D86: Z2-Programme Mentor (HC Managed) | E86: Full Time Employee | F86: White (South Africa) | G86: Male | H86: 30 - 39 | I86: FNB Retail Financial Resource Management (Anina Siriram) | J86: South Africa | K86: FNB | L86: 85500002046 FNB Retail Financial Resource Management | M86: Financial Resources Analyst | N86: 6 - 10 Years | O86: Financial Resources Management | P86: 5609305 | Q86: Hugh Bouwer | R86: Full Time Employee | S86: White (South Africa) | T86: Male | U86: 20 - 29 | V86: RMBSA Global Markets Technical Risk Advisory (Gareth Schumann) | W86: South Africa | X86: RMB | Y86: 77800000THR RMBSA Global Markets Technical Risk Advisory | Z86: Quantitative Risk Analyst | AA86: 3 - 5 Years | AB86: Operational Risk | AC86: Create Mentorship Event for Hugh Bouwer with Kevin Myers | AD86: 45139 | AE86: 45535
A87: 4643321 | B87: Kevin Hu | C87: Actuarial Science Mentoring Programme | D87: Z2-Programme Mentor (HC Managed) | E87: Full Time Employee | F87: Coloured (South Africa) | G87: Male | H87: 30 - 39 | I87: Group ERM Credit Risk Control (Engelbert Meyer) | J87: South Africa | K87: FirstRand Corporate Centre | L87: 20200006711 FRCC ERM Credit Risk Control | M87: Credit Model Standards and Governance Lead | N87: 11 -15 Years | O87: Operational Risk | P87: 5612144 | Q87: Diaan Dietrichsen (Terminated) | S87: White (South Africa) | T87: Male | U87: 20 - 29 | W87: South Africa | AA87: 3 - 5 Years | AC87: Create Mentorship Event for Diaan Dietrichsen (Terminated) with Kevin Hu | AD87: 45139 | AE87: 45535
A88: 5478960 | B88: Henry Lesar | D88: Career Mentor | E88: Full Time Employee | F88: Coloured (South Africa) | G88: Male | H88: 40 - 49 | I88: CDO Kernel Customer IT (Craig Coombs) | J88: South Africa | K88: FNB | L88: 79000005746 CDO Kernel CIS | M88: Application Development Manager | N88: 3 - 5 Years | O88: IT Development | P88: 5535093 | Q88: Maggie Nkoana | R88: Full Time Employee | S88: African (South Africa) | T88: Female | U88: 40 - 49 | V88: FNB Chief Risk Office PMO (Olwethu Vuyo Nkosi Bodlani) | W88: South Africa | X88: FNB | Y88: 39400008595 FNB Chief Risk Office PMO | Z88: Business Analyst | AA88: 3 - 5 Years | AB88: Process and Business Analysis | AC88: Create Mentorship Event for Maggie Nkoana with Henry Lesar | AD88: 45271
A89: 7552793 | B89: Theo Ngoma | D89: Career Mentor | E89: Full Time Employee | F89: African (South Africa) | G89: Female | H89: 30 - 39 | I89: CDO Infrastructure and Security Services (Ntswaki Lecage) | J89: South Africa | K89: FNB | L89: 20700005266 CDO Infrastructure and Security Services Command Centre | M89: Enterprise Systems Manager | N89: 3 - 5 Years | O89: System Design and Administration | P89: 3475697 | Q89: Nomvuselelo Ntuli | R89: OBR With Fixed Pay | S89: African (South Africa) | T89: Female | U89: 30 - 39 | V89: FNB Points of Presence (Noma Bozwana) | W89: South Africa | X89: FNB | Y89: 771034000 FNB POP Branch Delivery Port Alfred | Z89: Branch Advisor FAIS | AA89: 3 - 5 Years | AB89: Client Services Support and Delivery | AC89: Create Mentorship Event for Nomvuselelo Ntuli with Theo Ngoma | AD89: 45271 | AE89: 45382
A90: 7552793 | B90: Theo Ngoma | D90: Leadership Mentor | E90: Full Time Employee | F90: African (South Africa) | G90: Female | H90: 30 - 39 | I90: CDO Infrastructure and Security Services (Ntswaki Lecage) | J90: South Africa | K90: FNB | L90: 20700005266 CDO Infrastructure and Security Services Command Centre | M90: Enterprise Systems Manager | N90: 3 - 5 Years | O90: System Design and Administration | P90: 4844777 | Q90: Amanda Mene | R90: OBR With Fixed Pay | S90: African (South Africa) | T90: Female | U90: 30 - 39 | V90: FNB Points of Presence (Noma Bozwana) | W90: South Africa | X90: FNB | Y90: 771034000 FNB POP Branch Delivery Port Alfred | Z90: Branch Advisor FAIS | AA90: 11 -15 Years | AB90: Client Services Support and Delivery | AC90: Create Mentorship Event for Amanda Mene with Theo Ngoma | AD90: 45271 | AE90: 45352
A91: 3354423 | B91: Dorah Mohlopi | C91: performance goal | D91: Leadership Mentor | E91: Full Time Employee | F91: African (South Africa) | G91: Female | H91: 40 - 49 | I91: FNB Personal Core Banking (Malesela Rankapole) | J91: South Africa | K91: FNB | L91: 48100003462 FNB Personal Core Banking Retail Sales | M91: Growth Specialist | N91: 16 - 20 Years | O91: Business Development | P91: 7547056 | Q91: Pitsi Mnguni | R91: Full Time Employee | S91: African (South Africa) | T91: Female | U91: 40 - 49 | V91: FNB Points of Presence (Phumzile Mbele) | W91: South Africa | X91: FNB | Y91: 771079500 FNB POP Branch Delivery Bryanston | Z91: Branch Controller | AA91: 11 -15 Years | AB91: Administration | AC91: Create Mentorship Event for Pitsi Mnguni with Dorah Mohlopi | AD91: 45272 | AE91: 45638
A92: 3560643 | B92: Andries Shuping | C92: I want to be able to lead a highly motivated team which is always hungry for success. | D92: Leadership Mentor | E92: Full Time Employee | F92: African (South Africa) | G92: Male | H92: 40 - 49 | I92: FNB Points of Presence (Brian Wellsted) | J92: South Africa | K92: FNB | L92: 771042800 FNB POP Branch Delivery White River | M92: Local Market Manager | N92: 16 - 20 Years | O92: Client Relationship Management | P92: 3556611 | Q92: Sandile Nkosi | R92: Full Time Employee | S92: African (South Africa) | T92: Male | U92: 40 - 49 | V92: FNB Points of Presence (Brian Wellsted) | W92: South Africa | X92: FNB | Y92: 7710102900 FNB POP Branch Delivery Elukwatini | Z92: Associate | AA92: 16 - 20 Years | AB92: Client Relationship Management | AC92: Create Mentorship Event for Sandile Nkosi with Andries Shuping | AD92: 45271 | AE92: 45565
A93: 3105857 | B93: Nomvula Luphoko | C93: To help me navigate in to the new role, especially with sales and service. And for my branch not to peform below 400. | D93: Career Mentor | E93: Full Time Employee | F93: African (South Africa) | G93: Female | H93: 40 - 49 | I93: FNB Points of Presence (Tshwarelo Malele) | J93: South Africa | K93: FNB | L93: 7710110800 FNB POP Branch Delivery Kabokweni Plaza | M93: Branch Administrator | N93: 16 - 20 Years | O93: Administration | P93: 4717082 | Q93: Delisiwe Chilwane | R93: Full Time Employee | S93: African (South Africa) | T93: Female | U93: 30 - 39 | V93: FNB Points of Presence (Nondumiso Mthembu) | W93: South Africa | X93: FNB | Y93: 7710452300 FNB POP Nelspruit Crossing Centre | Z93: Branch Controller | AA93: 11 -15 Years | AB93: Administration | AC93: Create Mentorship Event for Delisiwe Chilwane with Nomvula Luphoko | AD93: 45279 | AE93: 45645
A94: 2966794 | B94: Avashni Singh | D94: Leadership Mentor | E94: Full Time Employee | F94: Indian (South Africa) | G94: Female | H94: 50 - 59 | I94: FNB Points of Presence (Pam Pitout) | J94: South Africa | K94: FNB | L94: 771006200 FNB POP Branch Delivery Pine Crest | M94: Local Market Manager | N94: >20 Years | O94: Client Relationship Management | P94: 2221543 | Q94: Fazila Khan | R94: Full Time Employee | S94: Indian (South Africa) | T94: Female | U94: 50 - 59 | V94: FNB Points of Presence (Avashni Singh) | W94: South Africa | X94: FNB | Y94: 771083500 FNB POP Branch Delivery The Pavilion | Z94: Associate | AA94: >20 Years | AB94: Client Relationship Management | AC94: Create Mentorship Event for Fazila Khan with Avashni Singh | AD94: 45267 | AE94: 45267
A95: 3221776 | B95: Bomikazi Sekoala | D95: Leadership Mentor | E95: Full Time Employee | F95: African (South Africa) | G95: Female | H95: 40 - 49 | I95: FNB Points of Presence (Kobus Steenkamp) | J95: South Africa | K95: FNB | L95: 771043400 FNB POP Branch Delivery Zastron | M95: Associate | N95: 16 - 20 Years | O95: Client Relationship Management | P95: 5393639 | Q95: Madika Makgeletsi | R95: OBR With Fixed Pay | S95: African (South Africa) | T95: Female | U95: 30 - 39 | V95: FNB Points of Presence (Thabiso Kutwane) | W95: South Africa | X95: FNB | Y95: 7710993900 FNB POP BRANCH DELIVERY PALM SPRINGS MALL | Z95: Branch Advisor FAIS | AA95: 3 - 5 Years | AB95: Client Services Support and Delivery | AC95: Create Mentorship Event for Madika Makgeletsi with Bomikazi Sekoala | AD95: 45295 | AE95: 45322
A96: 2966794 | B96: Avashni Singh | D96: Leadership Mentor | E96: Full Time Employee | F96: Indian (South Africa) | G96: Female | H96: 50 - 59 | I96: FNB Points of Presence (Pam Pitout) | J96: South Africa | K96: FNB | L96: 771006200 FNB POP Branch Delivery Pine Crest | M96: Local Market Manager | N96: >20 Years | O96: Client Relationship Management | P96: 3561372 | Q96: Thuthu Mnyandu | R96: Full Time Employee | S96: African (South Africa) | T96: Female | U96: 30 - 39 | V96: FNB Points of Presence (Susan Naicker) | W96: South Africa | X96: FNB | Y96: 771045100 FNB POP Branch Delivery New Germany | Z96: Universal Advisor Lead | AA96: 3 - 5 Years | AB96: Client Experience and Value Management | AC96: Create Mentorship Event for Thuthu Mnyandu with Avashni Singh | AD96: 45322 | AE96: 45657
A97: 3418626 | B97: Pieter Smit | C97: In training | D97: Leadership Mentor | E97: Full Time Employee | F97: White (South Africa) | G97: Male | H97: 30 - 39 | I97: FNB Points of Presence (Frans Esterhuyse) | J97: South Africa | K97: FNB | L97: 7710959900 FNB POP Risk In Branch Monitoring Team | M97: Process and Risk Manager | N97: 16 - 20 Years | O97: Operational Risk | P97: 2733994 | Q97: Anna Van Pletzen | R97: Full Time Employee | S97: White (South Africa) | T97: Female | U97: 40 - 49 | V97: FNB Points of Presence (Lee Ainslie) | W97: South Africa | X97: FNB | Y97: 771032600 FNB POP Branch Delivery Parys | Z97: Branch Delivery Sales and Service Team Leader | AA97: >20 Years | AB97: Direct Sales | AC97: Create Mentorship Event for Anna Van Pletzen with Pieter Smit | AD97: 45292 | AE97: 45382
A98: 3572323 | B98: Maserame Makwakwa (Terminated) | D98: Leadership Mentor | F98: African (South Africa) | G98: Female | H98: 30 - 39 | J98: South Africa | N98: 6 - 10 Years | P98: 5056268 | Q98: Ruth Raseemela | R98: OBR With Fixed Pay | S98: African (South Africa) | T98: Female | U98: 30 - 39 | V98: FNB Point of Presence (Dineo Mbalati) | W98: South Africa | X98: FNB | Y98: 771025000 FNB POP Branch Delivery Festival Mall | Z98: Branch Advisor FAIS | AA98: 6 - 10 Years | AB98: Client Services Support and Delivery | AC98: Create Mentorship Event for Ruth Raseemela with Maserame Makwakwa (Terminated) | AD98: 45308
A99: 3555933 | B99: Tshidiso Noge | D99: Leadership Mentor | E99: Full Time Employee | F99: African (South Africa) | G99: Male | H99: 30 - 39 | I99: FNB Points of Presence (Lungi Nsibanyoni) | J99: South Africa | K99: FNB | L99: 7710437300 FNB POP Branch Delivery Constantia Kloof | M99: Branch Controller | N99: 6 - 10 Years | O99: Administration | P99: 3716422 | Q99: Bongani Kgoedi | R99: OBR With Fixed Pay | S99: African (South Africa) | T99: Male | U99: 40 - 49 | V99: FNB Points of Presence (Paballo Kgolane) | W99: South Africa | X99: FNB | Y99: 771063300 FNB POP Branch Delivery Jane Furse | Z99: Branch Advisor FAIS | AA99: 11 -15 Years | AB99: Client Services Support and Delivery | AC99: Create Mentorship Event for Bongani Kgoedi with Tshidiso Noge | AD99: 45313 | AE99: 45639
A100: 2416824 | B100: Charles Thulani Nkosi | D100: Career Mentor | E100: Full Time Employee | F100: African (South Africa) | G100: Male | H100: 40 - 49 | I100: FNB Points of Presence (Dima Thaba) | J100: South Africa | K100: FNB | L100: 7710237800 FNB POP Regional Office Gauteng North | M100: Area Manager | N100: >20 Years | O100: Client Services Support and Delivery | P100: 3769984 | Q100: Siyabonga Mzimela | R100: Full Time Employee | S100: African (South Africa) | T100: Male | U100: 30 - 39 | V100: FNB Points of Presence (Musa Vukeya) | W100: South Africa | X100: FNB | Y100: 7710405800 FNB POP Commercial Collaboration | Z100: Key Accounts Manager | AA100: 11 -15 Years | AB100: Client Relationship Management | AC100: Create Mentorship Event for Siyabonga Mzimela with Charles Thulani Nkosi | AD100: 45271 | AE100: 45474
...

Sheet Mentor Pool
A1: Total in Workday | B1: =COUNTA('Paste - Mentors'!B4:B5000) -> 926 | D1: Available | E1: =COUNTIF(G4:G948,"Available") -> 805
C2: =IFERROR(VLOOKUP(E1,'Paste - Mentors'!$A:$B,2,0),"")
A3: Employee ID | B3: Mentor Name | C3: Mentor Type(s) | D3: Franchise | E3: Country | F3: Active Mentees (Workday) | G3: Capacity Status | H3: In Programme? (auto-check)
A4: ='Paste - Mentors'!A4 -> 5183472 | B4: =IFERROR(VLOOKUP(A4,'Paste - Mentors'!$A:$B,2,0),"") -> Gerald Maunda | C4: =IFERROR(VLOOKUP(A4,'Paste - Mentors'!$A:$D,4,0),"") -> Career Mentor | D4: =IFERROR(VLOOKUP(A4,'Paste - Mentors'!$A:$F,6,0),"") -> FNB | E4: =IFERROR(VLOOKUP(A4,'Paste - Mentors'!$A:$E,5,0),"") -> Zambia | F4: =IF(A4="","",COUNTIFS('Paste - Relationships'!$A:$A,A4,'Paste - Relationships'!$AE:$AE,"")) -> 0 | G4: =IF(A4="","",IF(F4>=3,"At Capacity",IF(F4=0,"Available","Has Capacity"))) -> Available | H4: =IF(A4="","",IF(COUNTIF('Programme Mentors'!$A:$A,A4)>0,"Enrolled","—")) -> —
A5: ='Paste - Mentors'!A5 -> 5495989 | B5: =IFERROR(VLOOKUP(A5,'Paste - Mentors'!$A:$B,2,0),"") -> Bonolo Molebatsi | C5: =IFERROR(VLOOKUP(A5,'Paste - Mentors'!$A:$D,4,0),"") -> Career Mentor | D5: =IFERROR(VLOOKUP(A5,'Paste - Mentors'!$A:$F,6,0),"") -> FNB | E5: =IFERROR(VLOOKUP(A5,'Paste - Mentors'!$A:$E,5,0),"") -> Botswana | F5: =IF(A5="","",COUNTIFS('Paste - Relationships'!$A:$A,A5,'Paste - Relationships'!$AE:$AE,"")) -> 1 | G5: =IF(A5="","",IF(F5>=3,"At Capacity",IF(F5=0,"Available","Has Capacity"))) -> Has Capacity | H5: =IF(A5="","",IF(COUNTIF('Programme Mentors'!$A:$A,A5)>0,"Enrolled","—")) -> —
A6: ='Paste - Mentors'!A6 -> 5009642 | B6: =IFERROR(VLOOKUP(A6,'Paste - Mentors'!$A:$B,2,0),"") -> Otisitswe Faith Rathedi | C6: =IFERROR(VLOOKUP(A6,'Paste - Mentors'!$A:$D,4,0),"") -> Career Mentor Leadership Mentor | D6: =IFERROR(VLOOKUP(A6,'Paste - Mentors'!$A:$F,6,0),"") -> FNB | E6: =IFERROR(VLOOKUP(A6,'Paste - Mentors'!$A:$E,5,0),"") -> Botswana | F6: =IF(A6="","",COUNTIFS('Paste - Relationships'!$A:$A,A6,'Paste - Relationships'!$AE:$AE,"")) -> 1 | G6: =IF(A6="","",IF(F6>=3,"At Capacity",IF(F6=0,"Available","Has Capacity"))) -> Has Capacity | H6: =IF(A6="","",IF(COUNTIF('Programme Mentors'!$A:$A,A6)>0,"Enrolled","—")) -> —
A7: ='Paste - Mentors'!A7 -> 5109140 | B7: =IFERROR(VLOOKUP(A7,'Paste - Mentors'!$A:$B,2,0),"") -> Bydon Longwe | C7: =IFERROR(VLOOKUP(A7,'Paste - Mentors'!$A:$D,4,0),"") -> Career Mentor | D7: =IFERROR(VLOOKUP(A7,'Paste - Mentors'!$A:$F,6,0),"") -> FNB | E7: =IFERROR(VLOOKUP(A7,'Paste - Mentors'!$A:$E,5,0),"") -> South Africa | F7: =IF(A7="","",COUNTIFS('Paste - Relationships'!$A:$A,A7,'Paste - Relationships'!$AE:$AE,"")) -> 1 | G7: =IF(A7="","",IF(F7>=3,"At Capacity",IF(F7=0,"Available","Has Capacity"))) -> Has Capacity | H7: =IF(A7="","",IF(COUNTIF('Programme Mentors'!$A:$A,A7)>0,"Enrolled","—")) -> —
A8: ='Paste - Mentors'!A8 -> 4946073 | B8: =IFERROR(VLOOKUP(A8,'Paste - Mentors'!$A:$B,2,0),"") -> Patrick Bontsibokae | C8: =IFERROR(VLOOKUP(A8,'Paste - Mentors'!$A:$D,4,0),"") -> Career Mentor | D8: =IFERROR(VLOOKUP(A8,'Paste - Mentors'!$A:$F,6,0),"") -> FNB | E8: =IFERROR(VLOOKUP(A8,'Paste - Mentors'!$A:$E,5,0),"") -> Botswana | F8: =IF(A8="","",COUNTIFS('Paste - Relationships'!$A:$A,A8,'Paste - Relationships'!$AE:$AE,"")) -> 0 | G8: =IF(A8="","",IF(F8>=3,"At Capacity",IF(F8=0,"Available","Has Capacity"))) -> Available | H8: =IF(A8="","",IF(COUNTIF('Programme Mentors'!$A:$A,A8)>0,"Enrolled","—")) -> —
A9: ='Paste - Mentors'!A9 -> 4997751 | B9: =IFERROR(VLOOKUP(A9,'Paste - Mentors'!$A:$B,2,0),"") -> Caroline Kepaletswe | C9: =IFERROR(VLOOKUP(A9,'Paste - Mentors'!$A:$D,4,0),"") -> Career Mentor | D9: =IFERROR(VLOOKUP(A9,'Paste - Mentors'!$A:$F,6,0),"") -> FNB | E9: =IFERROR(VLOOKUP(A9,'Paste - Mentors'!$A:$E,5,0),"") -> Botswana | F9: =IF(A9="","",COUNTIFS('Paste - Relationships'!$A:$A,A9,'Paste - Relationships'!$AE:$AE,"")) -> 1 | G9: =IF(A9="","",IF(F9>=3,"At Capacity",IF(F9=0,"Available","Has Capacity"))) -> Has Capacity | H9: =IF(A9="","",IF(COUNTIF('Programme Mentors'!$A:$A,A9)>0,"Enrolled","—")) -> —
A10: ='Paste - Mentors'!A10 -> 4714849 | B10: =IFERROR(VLOOKUP(A10,'Paste - Mentors'!$A:$B,2,0),"") -> Chapita Mbuzi | C10: =IFERROR(VLOOKUP(A10,'Paste - Mentors'!$A:$D,4,0),"") -> Career Mentor | D10: =IFERROR(VLOOKUP(A10,'Paste - Mentors'!$A:$F,6,0),"") -> FNB | E10: =IFERROR(VLOOKUP(A10,'Paste - Mentors'!$A:$E,5,0),"") -> Zambia | F10: =IF(A10="","",COUNTIFS('Paste - Relationships'!$A:$A,A10,'Paste - Relationships'!$AE:$AE,"")) -> 0 | G10: =IF(A10="","",IF(F10>=3,"At Capacity",IF(F10=0,"Available","Has Capacity"))) -> Available | H10: =IF(A10="","",IF(COUNTIF('Programme Mentors'!$A:$A,A10)>0,"Enrolled","—")) -> —
A11: ='Paste - Mentors'!A11 -> 3872521 | B11: =IFERROR(VLOOKUP(A11,'Paste - Mentors'!$A:$B,2,0),"") -> Wiza Phiri | C11: =IFERROR(VLOOKUP(A11,'Paste - Mentors'!$A:$D,4,0),"") -> Career Mentor | D11: =IFERROR(VLOOKUP(A11,'Paste - Mentors'!$A:$F,6,0),"") -> FNB | E11: =IFERROR(VLOOKUP(A11,'Paste - Mentors'!$A:$E,5,0),"") -> Zambia | F11: =IF(A11="","",COUNTIFS('Paste - Relationships'!$A:$A,A11,'Paste - Relationships'!$AE:$AE,"")) -> 0 | G11: =IF(A11="","",IF(F11>=3,"At Capacity",IF(F11=0,"Available","Has Capacity"))) -> Available | H11: =IF(A11="","",IF(COUNTIF('Programme Mentors'!$A:$A,A11)>0,"Enrolled","—")) -> —
A12: ='Paste - Mentors'!A12 -> 4930088 | B12: =IFERROR(VLOOKUP(A12,'Paste - Mentors'!$A:$B,2,0),"") -> Retselisitsoe Sylvia Khet'semane | C12: =IFERROR(VLOOKUP(A12,'Paste - Mentors'!$A:$D,4,0),"") -> Career Mentor | D12: =IFERROR(VLOOKUP(A12,'Paste - Mentors'!$A:$F,6,0),"") -> FNB | E12: =IFERROR(VLOOKUP(A12,'Paste - Mentors'!$A:$E,5,0),"") -> Lesotho | F12: =IF(A12="","",COUNTIFS('Paste - Relationships'!$A:$A,A12,'Paste - Relationships'!$AE:$AE,"")) -> 0 | G12: =IF(A12="","",IF(F12>=3,"At Capacity",IF(F12=0,"Available","Has Capacity"))) -> Available | H12: =IF(A12="","",IF(COUNTIF('Programme Mentors'!$A:$A,A12)>0,"Enrolled","—")) -> —
A13: ='Paste - Mentors'!A13 -> 4989171 | B13: =IFERROR(VLOOKUP(A13,'Paste - Mentors'!$A:$B,2,0),"") -> Borethe Mogwe | C13: =IFERROR(VLOOKUP(A13,'Paste - Mentors'!$A:$D,4,0),"") -> Career Mentor | D13: =IFERROR(VLOOKUP(A13,'Paste - Mentors'!$A:$F,6,0),"") -> FNB | E13: =IFERROR(VLOOKUP(A13,'Paste - Mentors'!$A:$E,5,0),"") -> Botswana | F13: =IF(A13="","",COUNTIFS('Paste - Relationships'!$A:$A,A13,'Paste - Relationships'!$AE:$AE,"")) -> 2 | G13: =IF(A13="","",IF(F13>=3,"At Capacity",IF(F13=0,"Available","Has Capacity"))) -> Has Capacity | H13: =IF(A13="","",IF(COUNTIF('Programme Mentors'!$A:$A,A13)>0,"Enrolled","—")) -> —
A14: ='Paste - Mentors'!A14 -> 4804473 | B14: =IFERROR(VLOOKUP(A14,'Paste - Mentors'!$A:$B,2,0),"") -> Gofaone Mokalake | C14: =IFERROR(VLOOKUP(A14,'Paste - Mentors'!$A:$D,4,0),"") -> Career Mentor Leadership Mentor | D14: =IFERROR(VLOOKUP(A14,'Paste - Mentors'!$A:$F,6,0),"") -> FNB | E14: =IFERROR(VLOOKUP(A14,'Paste - Mentors'!$A:$E,5,0),"") -> Botswana | F14: =IF(A14="","",COUNTIFS('Paste - Relationships'!$A:$A,A14,'Paste - Relationships'!$AE:$AE,"")) -> 0 | G14: =IF(A14="","",IF(F14>=3,"At Capacity",IF(F14=0,"Available","Has Capacity"))) -> Available | H14: =IF(A14="","",IF(COUNTIF('Programme Mentors'!$A:$A,A14)>0,"Enrolled","—")) -> —
A15: ='Paste - Mentors'!A15 -> 4868455 | B15: =IFERROR(VLOOKUP(A15,'Paste - Mentors'!$A:$B,2,0),"") -> Tshepo Sentle | C15: =IFERROR(VLOOKUP(A15,'Paste - Mentors'!$A:$D,4,0),"") -> Career Mentor | D15: =IFERROR(VLOOKUP(A15,'Paste - Mentors'!$A:$F,6,0),"") -> FNB | E15: =IFERROR(VLOOKUP(A15,'Paste - Mentors'!$A:$E,5,0),"") -> Botswana | F15: =IF(A15="","",COUNTIFS('Paste - Relationships'!$A:$A,A15,'Paste - Relationships'!$AE:$AE,"")) -> 0 | G15: =IF(A15="","",IF(F15>=3,"At Capacity",IF(F15=0,"Available","Has Capacity"))) -> Available | H15: =IF(A15="","",IF(COUNTIF('Programme Mentors'!$A:$A,A15)>0,"Enrolled","—")) -> —
... A947: ='Paste - Mentors'!A947 -> 0 | B947: =IFERROR(VLOOKUP(A947,'Paste - Mentors'!$A:$B,2,0),"") | C947: =IFERROR(VLOOKUP(A947,'Paste - Mentors'!$A:$D,4,0),"") | D947: =IFERROR(VLOOKUP(A947,'Paste - Mentors'!$A:$F,6,0),"") | E947: =IFERROR(VLOOKUP(A947,'Paste - Mentors'!$A:$E,5,0),"") | F947: =IF(A947="","",COUNTIFS('Paste - Relationships'!$A:$A,A947,'Paste - Relationships'!$AE:$AE,"")) -> 0 | G947: =IF(A947="","",IF(F947>=3,"At Capacity",IF(F947=0,"Available","Has Capacity"))) -> Available | H947: =IF(A947="","",IF(COUNTIF('Programme Mentors'!$A:$A,A947)>0,"Enrolled","—")) -> —

Sheet Programme Mentors
A1: Total Enrolled Mentors | B1: =COUNTA(A4:A298) -> 0 | D1: Not on Workday (Action Req) | E1: =COUNTIF(G4:G298,"Not Found") -> 0
A3: Employee ID | B3: Full Name | C3: Max Mentees (default=3) | D3: Date Added to Programme | E3: Supervisory Org | F3: Job Title | G3: Workday Status | H3: Current Mentees | I3: Remaining Capacity
B4: =IFERROR(VLOOKUP(A4,'Paste - Mentors'!$A:$B,2,0),"") | E4: =IFERROR(VLOOKUP(A4,'Paste - Mentors'!$A:$G,7,0),"") | F4: =IFERROR(VLOOKUP(A4,'Paste - Mentors'!$A:$K,11,0),"") | G4: =IF(A4="","",IF(COUNTIF('Paste - Mentors'!$A:$A,A4)>0,"Registered","Not Found")) | H4: =IF(A4="","",COUNTIF('Intern Monitoring'!$D$4:$D$203,B4)) | I4: =IF(A4="","",IFERROR(IF(C4="",3,C4)-IF(H4="",0,H4),"-"))
B5: =IFERROR(VLOOKUP(A5,'Paste - Mentors'!$A:$B,2,0),"") | E5: =IFERROR(VLOOKUP(A5,'Paste - Mentors'!$A:$G,7,0),"") | F5: =IFERROR(VLOOKUP(A5,'Paste - Mentors'!$A:$K,11,0),"") | G5: =IF(A5="","",IF(COUNTIF('Paste - Mentors'!$A:$A,A5)>0,"Registered","Not Found")) | H5: =IF(A5="","",COUNTIF('Intern Monitoring'!$D$4:$D$203,B5)) | I5: =IF(A5="","",IFERROR(IF(C5="",3,C5)-IF(H5="",0,H5),"-"))
B6: =IFERROR(VLOOKUP(A6,'Paste - Mentors'!$A:$B,2,0),"") | E6: =IFERROR(VLOOKUP(A6,'Paste - Mentors'!$A:$G,7,0),"") | F6: =IFERROR(VLOOKUP(A6,'Paste - Mentors'!$A:$K,11,0),"") | G6: =IF(A6="","",IF(COUNTIF('Paste - Mentors'!$A:$A,A6)>0,"Registered","Not Found")) | H6: =IF(A6="","",COUNTIF('Intern Monitoring'!$D$4:$D$203,B6)) | I6: =IF(A6="","",IFERROR(IF(C6="",3,C6)-IF(H6="",0,H6),"-"))
B7: =IFERROR(VLOOKUP(A7,'Paste - Mentors'!$A:$B,2,0),"") | E7: =IFERROR(VLOOKUP(A7,'Paste - Mentors'!$A:$G,7,0),"") | F7: =IFERROR(VLOOKUP(A7,'Paste - Mentors'!$A:$K,11,0),"") | G7: =IF(A7="","",IF(COUNTIF('Paste - Mentors'!$A:$A,A7)>0,"Registered","Not Found")) | H7: =IF(A7="","",COUNTIF('Intern Monitoring'!$D$4:$D$203,B7)) | I7: =IF(A7="","",IFERROR(IF(C7="",3,C7)-IF(H7="",0,H7),"-"))
B8: =IFERROR(VLOOKUP(A8,'Paste - Mentors'!$A:$B,2,0),"") | E8: =IFERROR(VLOOKUP(A8,'Paste - Mentors'!$A:$G,7,0),"") | F8: =IFERROR(VLOOKUP(A8,'Paste - Mentors'!$A:$K,11,0),"") | G8: =IF(A8="","",IF(COUNTIF('Paste - Mentors'!$A:$A,A8)>0,"Registered","Not Found")) | H8: =IF(A8="","",COUNTIF('Intern Monitoring'!$D$4:$D$203,B8)) | I8: =IF(A8="","",IFERROR(IF(C8="",3,C8)-IF(H8="",0,H8),"-"))
B9: =IFERROR(VLOOKUP(A9,'Paste - Mentors'!$A:$B,2,0),"") | E9: =IFERROR(VLOOKUP(A9,'Paste - Mentors'!$A:$G,7,0),"") | F9: =IFERROR(VLOOKUP(A9,'Paste - Mentors'!$A:$K,11,0),"") | G9: =IF(A9="","",IF(COUNTIF('Paste - Mentors'!$A:$A,A9)>0,"Registered","Not Found")) | H9: =IF(A9="","",COUNTIF('Intern Monitoring'!$D$4:$D$203,B9)) | I9: =IF(A9="","",IFERROR(IF(C9="",3,C9)-IF(H9="",0,H9),"-"))
B10: =IFERROR(VLOOKUP(A10,'Paste - Mentors'!$A:$B,2,0),"") | E10: =IFERROR(VLOOKUP(A10,'Paste - Mentors'!$A:$G,7,0),"") | F10: =IFERROR(VLOOKUP(A10,'Paste - Mentors'!$A:$K,11,0),"") | G10: =IF(A10="","",IF(COUNTIF('Paste - Mentors'!$A:$A,A10)>0,"Registered","Not Found")) | H10: =IF(A10="","",COUNTIF('Intern Monitoring'!$D$4:$D$203,B10)) | I10: =IF(A10="","",IFERROR(IF(C10="",3,C10)-IF(H10="",0,H10),"-"))
B11: =IFERROR(VLOOKUP(A11,'Paste - Mentors'!$A:$B,2,0),"") | E11: =IFERROR(VLOOKUP(A11,'Paste - Mentors'!$A:$G,7,0),"") | F11: =IFERROR(VLOOKUP(A11,'Paste - Mentors'!$A:$K,11,0),"") | G11: =IF(A11="","",IF(COUNTIF('Paste - Mentors'!$A:$A,A11)>0,"Registered","Not Found")) | H11: =IF(A11="","",COUNTIF('Intern Monitoring'!$D$4:$D$203,B11)) | I11: =IF(A11="","",IFERROR(IF(C11="",3,C11)-IF(H11="",0,H11),"-"))
B12: =IFERROR(VLOOKUP(A12,'Paste - Mentors'!$A:$B,2,0),"") | E12: =IFERROR(VLOOKUP(A12,'Paste - Mentors'!$A:$G,7,0),"") | F12: =IFERROR(VLOOKUP(A12,'Paste - Mentors'!$A:$K,11,0),"") | G12: =IF(A12="","",IF(COUNTIF('Paste - Mentors'!$A:$A,A12)>0,"Registered","Not Found")) | H12: =IF(A12="","",COUNTIF('Intern Monitoring'!$D$4:$D$203,B12)) | I12: =IF(A12="","",IFERROR(IF(C12="",3,C12)-IF(H12="",0,H12),"-"))
B13: =IFERROR(VLOOKUP(A13,'Paste - Mentors'!$A:$B,2,0),"") | E13: =IFERROR(VLOOKUP(A13,'Paste - Mentors'!$A:$G,7,0),"") | F13: =IFERROR(VLOOKUP(A13,'Paste - Mentors'!$A:$K,11,0),"") | G13: =IF(A13="","",IF(COUNTIF('Paste - Mentors'!$A:$A,A13)>0,"Registered","Not Found")) | H13: =IF(A13="","",COUNTIF('Intern Monitoring'!$D$4:$D$203,B13)) | I13: =IF(A13="","",IFERROR(IF(C13="",3,C13)-IF(H13="",0,H13),"-"))
B14: =IFERROR(VLOOKUP(A14,'Paste - Mentors'!$A:$B,2,0),"") | E14: =IFERROR(VLOOKUP(A14,'Paste - Mentors'!$A:$G,7,0),"") | F14: =IFERROR(VLOOKUP(A14,'Paste - Mentors'!$A:$K,11,0),"") | G14: =IF(A14="","",IF(COUNTIF('Paste - Mentors'!$A:$A,A14)>0,"Registered","Not Found")) | H14: =IF(A14="","",COUNTIF('Intern Monitoring'!$D$4:$D$203,B14)) | I14: =IF(A14="","",IFERROR(IF(C14="",3,C14)-IF(H14="",0,H14),"-"))
B15: =IFERROR(VLOOKUP(A15,'Paste - Mentors'!$A:$B,2,0),"") | E15: =IFERROR(VLOOKUP(A15,'Paste - Mentors'!$A:$G,7,0),"") | F15: =IFERROR(VLOOKUP(A15,'Paste - Mentors'!$A:$K,11,0),"") | G15: =IF(A15="","",IF(COUNTIF('Paste - Mentors'!$A:$A,A15)>0,"Registered","Not Found")) | H15: =IF(A15="","",COUNTIF('Intern Monitoring'!$D$4:$D$203,B15)) | I15: =IF(A15="","",IFERROR(IF(C15="",3,C15)-IF(H15="",0,H15),"-"))
... B203: =IFERROR(VLOOKUP(A203,'Paste - Mentors'!$A:$B,2,0),"") | E203: =IFERROR(VLOOKUP(A203,'Paste - Mentors'!$A:$G,7,0),"") | F203: =IFERROR(VLOOKUP(A203,'Paste - Mentors'!$A:$K,11,0),"") | G203: =IF(A203="","",IF(COUNTIF('Paste - Mentors'!$A:$A,A203)>0,"Registered","Not Found")) | H203: =IF(A203="","",COUNTIF('Intern Monitoring'!$D$4:$D$203,B203)) | I203: =IF(A203="","",IFERROR(IF(C203="",3,C203)-IF(H203="",0,H203),"-"))
B204: =IFERROR(VLOOKUP(A204,'Paste - Mentors'!$A:$B,2,0),"") | E204: =IFERROR(VLOOKUP(A204,'Paste - Mentors'!$A:$G,7,0),"") | F204: =IFERROR(VLOOKUP(A204,'Paste - Mentors'!$A:$K,11,0),"") | G204: =IF(A204="","",IF(COUNTIF('Paste - Mentors'!$A:$A,A204)>0,"Registered","Not Found")) | H204: =IF(A204="","",COUNTIF('Intern Monitoring'!$D$4:$D$203,B204)) | I204: =IF(A204="","",IF(C204="",3,C204)-H204)
B205: =IFERROR(VLOOKUP(A205,'Paste - Mentors'!$A:$B,2,0),"") | E205: =IFERROR(VLOOKUP(A205,'Paste - Mentors'!$A:$G,7,0),"") | F205: =IFERROR(VLOOKUP(A205,'Paste - Mentors'!$A:$K,11,0),"") | G205: =IF(A205="","",IF(COUNTIF('Paste - Mentors'!$A:$A,A205)>0,"Registered","Not Found")) | H205: =IF(A205="","",COUNTIF('Intern Monitoring'!$D$4:$D$203,B205)) | I205: =IF(A205="","",IF(C205="",3,C205)-H205)
B206: =IFERROR(VLOOKUP(A206,'Paste - Mentors'!$A:$B,2,0),"") | E206: =IFERROR(VLOOKUP(A206,'Paste - Mentors'!$A:$G,7,0),"") | F206: =IFERROR(VLOOKUP(A206,'Paste - Mentors'!$A:$K,11,0),"") | G206: =IF(A206="","",IF(COUNTIF('Paste - Mentors'!$A:$A,A206)>0,"Registered","Not Found")) | H206: =IF(A206="","",COUNTIF('Intern Monitoring'!$D$4:$D$203,B206)) | I206: =IF(A206="","",IF(C206="",3,C206)-H206)
B207: =IFERROR(VLOOKUP(A207,'Paste - Mentors'!$A:$B,2,0),"") | E207: =IFERROR(VLOOKUP(A207,'Paste - Mentors'!$A:$G,7,0),"") | F207: =IFERROR(VLOOKUP(A207,'Paste - Mentors'!$A:$K,11,0),"") | G207: =IF(A207="","",IF(COUNTIF('Paste - Mentors'!$A:$A,A207)>0,"Registered","Not Found")) | H207: =IF(A207="","",COUNTIF('Intern Monitoring'!$D$4:$D$203,B207)) | I207: =IF(A207="","",IF(C207="",3,C207)-H207)
B208: =IFERROR(VLOOKUP(A208,'Paste - Mentors'!$A:$B,2,0),"") | E208: =IFERROR(VLOOKUP(A208,'Paste - Mentors'!$A:$G,7,0),"") | F208: =IFERROR(VLOOKUP(A208,'Paste - Mentors'!$A:$K,11,0),"") | G208: =IF(A208="","",IF(COUNTIF('Paste - Mentors'!$A:$A,A208)>0,"Registered","Not Found")) | H208: =IF(A208="","",COUNTIF('Intern Monitoring'!$D$4:$D$203,B208)) | I208: =IF(A208="","",IF(C208="",3,C208)-H208)
B209: =IFERROR(VLOOKUP(A209,'Paste - Mentors'!$A:$B,2,0),"") | E209: =IFERROR(VLOOKUP(A209,'Paste - Mentors'!$A:$G,7,0),"") | F209: =IFERROR(VLOOKUP(A209,'Paste - Mentors'!$A:$K,11,0),"") | G209: =IF(A209="","",IF(COUNTIF('Paste - Mentors'!$A:$A,A209)>0,"Registered","Not Found")) | H209: =IF(A209="","",COUNTIF('Intern Monitoring'!$D$4:$D$203,B209)) | I209: =IF(A209="","",IF(C209="",3,C209)-H209)
B210: =IFERROR(VLOOKUP(A210,'Paste - Mentors'!$A:$B,2,0),"") | E210: =IFERROR(VLOOKUP(A210,'Paste - Mentors'!$A:$G,7,0),"") | F210: =IFERROR(VLOOKUP(A210,'Paste - Mentors'!$A:$K,11,0),"") | G210: =IF(A210="","",IF(COUNTIF('Paste - Mentors'!$A:$A,A210)>0,"Registered","Not Found")) | H210: =IF(A210="","",COUNTIF('Intern Monitoring'!$D$4:$D$203,B210)) | I210: =IF(A210="","",IF(C210="",3,C210)-H210)
B211: =IFERROR(VLOOKUP(A211,'Paste - Mentors'!$A:$B,2,0),"") | E211: =IFERROR(VLOOKUP(A211,'Paste - Mentors'!$A:$G,7,0),"") | F211: =IFERROR(VLOOKUP(A211,'Paste - Mentors'!$A:$K,11,0),"") | G211: =IF(A211="","",IF(COUNTIF('Paste - Mentors'!$A:$A,A211)>0,"Registered","Not Found")) | H211: =IF(A211="","",COUNTIF('Intern Monitoring'!$D$4:$D$203,B211)) | I211: =IF(A211="","",IF(C211="",3,C211)-H211)
B212: =IFERROR(VLOOKUP(A212,'Paste - Mentors'!$A:$B,2,0),"") | E212: =IFERROR(VLOOKUP(A212,'Paste - Mentors'!$A:$G,7,0),"") | F212: =IFERROR(VLOOKUP(A212,'Paste - Mentors'!$A:$K,11,0),"") | G212: =IF(A212="","",IF(COUNTIF('Paste - Mentors'!$A:$A,A212)>0,"Registered","Not Found")) | H212: =IF(A212="","",COUNTIF('Intern Monitoring'!$D$4:$D$203,B212)) | I212: =IF(A212="","",IF(C212="",3,C212)-H212)
B213: =IFERROR(VLOOKUP(A213,'Paste - Mentors'!$A:$B,2,0),"") | E213: =IFERROR(VLOOKUP(A213,'Paste - Mentors'!$A:$G,7,0),"") | F213: =IFERROR(VLOOKUP(A213,'Paste - Mentors'!$A:$K,11,0),"") | G213: =IF(A213="","",IF(COUNTIF('Paste - Mentors'!$A:$A,A213)>0,"Registered","Not Found")) | H213: =IF(A213="","",COUNTIF('Intern Monitoring'!$D$4:$D$203,B213)) | I213: =IF(A213="","",IF(C213="",3,C213)-H213)
B214: =IFERROR(VLOOKUP(A214,'Paste - Mentors'!$A:$B,2,0),"") | E214: =IFERROR(VLOOKUP(A214,'Paste - Mentors'!$A:$G,7,0),"") | F214: =IFERROR(VLOOKUP(A214,'Paste - Mentors'!$A:$K,11,0),"") | G214: =IF(A214="","",IF(COUNTIF('Paste - Mentors'!$A:$A,A214)>0,"Registered","Not Found")) | H214: =IF(A214="","",COUNTIF('Intern Monitoring'!$D$4:$D$203,B214)) | I214: =IF(A214="","",IF(C214="",3,C214)-H214)
B215: =IFERROR(VLOOKUP(A215,'Paste - Mentors'!$A:$B,2,0),"") | E215: =IFERROR(VLOOKUP(A215,'Paste - Mentors'!$A:$G,7,0),"") | F215: =IFERROR(VLOOKUP(A215,'Paste - Mentors'!$A:$K,11,0),"") | G215: =IF(A215="","",IF(COUNTIF('Paste - Mentors'!$A:$A,A215)>0,"Registered","Not Found")) | H215: =IF(A215="","",COUNTIF('Intern Monitoring'!$D$4:$D$203,B215)) | I215: =IF(A215="","",IF(C215="",3,C215)-H215)
... B298: =IFERROR(VLOOKUP(A298,'Paste - Mentors'!$A:$B,2,0),"") | E298: =IFERROR(VLOOKUP(A298,'Paste - Mentors'!$A:$G,7,0),"") | F298: =IFERROR(VLOOKUP(A298,'Paste - Mentors'!$A:$K,11,0),"") | G298: =IF(A298="","",IF(COUNTIF('Paste - Mentors'!$A:$A,A298)>0,"Registered","Not Found")) | H298: =IF(A298="","",COUNTIF('Intern Monitoring'!$D$4:$D$203,B298)) | I298: =IF(A298="","",IF(C298="",3,C298)-H298)

Sheet Intern Profiles
A1: Total Interns | B1: =COUNTA(A4:A203) -> 63
A3: Employee ID | B3: Full Name | C3: Cohort
A4: F8884130 | B4: Innocent Ntsako Chauke | C4: Cohort 1 - 2026
A5: F8884211 | B5: Zanele Mboweni | C5: Cohort 1 - 2026
A6: F8885591 | B6: Anelisa Mankayi | C6: Cohort 1 - 2026
A7: F8885847 | B7: Gift Sikhulile Mashele | C7: Cohort 1 - 2026
A8: F8885589 | B8: Gratitude Monareng | C8: Cohort 1 - 2026
A9: F8884143 | B9: Nkhensani Shibambo | C9: Cohort 1 - 2026
A10: F8884358 | B10: Chesley Gustav | C10: Cohort 1 - 2026
A11: F8885583 | B11: Kgothatso Phillep Lebese | C11: Cohort 1 - 2026
A12: F8885759 | B12: Kgotatso Madela | C12: Cohort 1 - 2026
A13: F8885825 | B13: Noluthando Ndlovu | C13: Cohort 1 - 2026
A14: F8885615 | B14: Ncediwe Mphantsi | C14: Cohort 1 - 2026
... A66: F8885692 | B66: Nondumiso Magongo | C66: Cohort 1 - 2026

Sheet Intern Monitoring
A1: Total Interns | B1: =COUNTA('Intern Profiles'!A4:A203) -> 63 | C1: Overdue – Book Now | D1: =COUNTIF(G4:G203,"Overdue*") -> 0 | E1: No Next Session | F1: =COUNTIFS(A4:A203,"<>",F4:F203,"") -> 200 | G1: Missed Sessions | H1: =COUNTIF(G4:G203,"Missed Session") -> 0
A2: 🔍 Type name or ID: | C2: =IFERROR(IF(B2="","",IF(ISNUMBER(VALUE(B2)),INDEX(A4:A203,MATCH(VALUE(B2),A4:A203,0)),INDEX(A4:A203,MATCH("*"&B2&"*",B4:B203,0)))),"No match") | D2: =IFERROR(IF(B2="","",IF(ISNUMBER(VALUE(B2)),INDEX(B4:B203,MATCH(VALUE(B2),A4:A203,0)),INDEX(B4:B203,MATCH("*"&B2&"*",B4:B203,0)))),"No match") | E2: =IFERROR(IF(B2="","",IF(ISNUMBER(VALUE(B2)),INDEX(C4:C203,MATCH(VALUE(B2),A4:A203,0)),INDEX(C4:C203,MATCH("*"&B2&"*",B4:B203,0)))),"No match") | F2: =IFERROR(IF(B2="","",IF(ISNUMBER(VALUE(B2)),INDEX(D4:D203,MATCH(VALUE(B2),A4:A203,0)),INDEX(D4:D203,MATCH("*"&B2&"*",B4:B203,0)))),"No match") | G2: =IFERROR(IF(B2="","",IF(ISNUMBER(VALUE(B2)),INDEX(G4:G203,MATCH(VALUE(B2),A4:A203,0)),INDEX(G4:G203,MATCH("*"&B2&"*",B4:B203,0)))),"No match")
A3: Employee ID (auto) | B3: Full Name (auto) | C3: Cohort (auto) | D3: Active Mentor (assign here) | E3: Last Session Date (auto from form) | F3: Next Session Date (auto from form) | G3: Session Health (auto) | H3: Notes
A4: ='Intern Profiles'!A4 -> F8884130 | B4: ='Intern Profiles'!B4 -> Innocent Ntsako Chauke | C4: ='Intern Profiles'!C4 -> Cohort 1 - 2026 | D4: =IF(A4="","",IFERROR(INDEX('Paste - Relationships'!$B$4:$B$800,MATCH(1,('Paste - Relationships'!$P$4:$P$800=VALUE(A4))*('Paste - Relationships'!$AE$4:$AE$800=""),0)),"")) | E4: =IFERROR(IF(A4="","",_xludf.maxifs('Session Logs'!$E:$E,'Session Logs'!$D:$D,B4,'Session Logs'!$C:$C,D4)),"") | F4: =IFERROR(IF(A4="","",_xludf.maxifs('Session Logs'!$I:$I,'Session Logs'!$D:$D,B4,'Session Logs'!$C:$C,D4,'Session Logs'!$I:$I,">"&TODAY())),"") | G4: =IF(A4="","",IF(D4="","No Mentor Assigned",IF(E4="","No Sessions Yet",IF(AND(F4<>"",F4<TODAY()),"Missed Session",IF(AND(TODAY()-E4>30,F4=""),"Overdue – Book Now",IF(TODAY()-E4>30,"Overdue – Session Booked","On Track")))))) -> No Mentor Assigned
A5: ='Intern Profiles'!A5 -> F8884211 | B5: ='Intern Profiles'!B5 -> Zanele Mboweni | C5: ='Intern Profiles'!C5 -> Cohort 1 - 2026 | D5: =IF(A5="","",IFERROR(INDEX('Paste - Relationships'!$B$4:$B$800,MATCH(1,('Paste - Relationships'!$P$4:$P$800=VALUE(A5))*('Paste - Relationships'!$AE$4:$AE$800=""),0)),"")) | E5: =IFERROR(IF(A5="","",_xludf.maxifs('Session Logs'!$E:$E,'Session Logs'!$D:$D,B5,'Session Logs'!$C:$C,D5)),"") | F5: =IFERROR(IF(A5="","",_xludf.maxifs('Session Logs'!$I:$I,'Session Logs'!$D:$D,B5,'Session Logs'!$C:$C,D5,'Session Logs'!$I:$I,">"&TODAY())),"") | G5: =IF(A5="","",IF(D5="","No Mentor Assigned",IF(E5="","No Sessions Yet",IF(AND(F5<>"",F5<TODAY()),"Missed Session",IF(AND(TODAY()-E5>30,F5=""),"Overdue – Book Now",IF(TODAY()-E5>30,"Overdue – Session Booked","On Track")))))) -> No Mentor Assigned
A6: ='Intern Profiles'!A6 -> F8885591 | B6: ='Intern Profiles'!B6 -> Anelisa Mankayi | C6: ='Intern Profiles'!C6 -> Cohort 1 - 2026 | D6: =IF(A6="","",IFERROR(INDEX('Paste - Relationships'!$B$4:$B$800,MATCH(1,('Paste - Relationships'!$P$4:$P$800=VALUE(A6))*('Paste - Relationships'!$AE$4:$AE$800=""),0)),"")) | E6: =IFERROR(IF(A6="","",_xludf.maxifs('Session Logs'!$E:$E,'Session Logs'!$D:$D,B6,'Session Logs'!$C:$C,D6)),"") | F6: =IFERROR(IF(A6="","",_xludf.maxifs('Session Logs'!$I:$I,'Session Logs'!$D:$D,B6,'Session Logs'!$C:$C,D6,'Session Logs'!$I:$I,">"&TODAY())),"") | G6: =IF(A6="","",IF(D6="","No Mentor Assigned",IF(E6="","No Sessions Yet",IF(AND(F6<>"",F6<TODAY()),"Missed Session",IF(AND(TODAY()-E6>30,F6=""),"Overdue – Book Now",IF(TODAY()-E6>30,"Overdue – Session Booked","On Track")))))) -> No Mentor Assigned
A7: ='Intern Profiles'!A7 -> F8885847 | B7: ='Intern Profiles'!B7 -> Gift Sikhulile Mashele | C7: ='Intern Profiles'!C7 -> Cohort 1 - 2026 | D7: =IF(A7="","",IFERROR(INDEX('Paste - Relationships'!$B$4:$B$800,MATCH(1,('Paste - Relationships'!$P$4:$P$800=VALUE(A7))*('Paste - Relationships'!$AE$4:$AE$800=""),0)),"")) | E7: =IFERROR(IF(A7="","",_xludf.maxifs('Session Logs'!$E:$E,'Session Logs'!$D:$D,B7,'Session Logs'!$C:$C,D7)),"") | F7: =IFERROR(IF(A7="","",_xludf.maxifs('Session Logs'!$I:$I,'Session Logs'!$D:$D,B7,'Session Logs'!$C:$C,D7,'Session Logs'!$I:$I,">"&TODAY())),"") | G7: =IF(A7="","",IF(D7="","No Mentor Assigned",IF(E7="","No Sessions Yet",IF(AND(F7<>"",F7<TODAY()),"Missed Session",IF(AND(TODAY()-E7>30,F7=""),"Overdue – Book Now",IF(TODAY()-E7>30,"Overdue – Session Booked","On Track")))))) -> No Mentor Assigned
A8: ='Intern Profiles'!A8 -> F8885589 | B8: ='Intern Profiles'!B8 -> Gratitude Monareng | C8: ='Intern Profiles'!C8 -> Cohort 1 - 2026 | D8: =IF(A8="","",IFERROR(INDEX('Paste - Relationships'!$B$4:$B$800,MATCH(1,('Paste - Relationships'!$P$4:$P$800=VALUE(A8))*('Paste - Relationships'!$AE$4:$AE$800=""),0)),"")) | E8: =IFERROR(IF(A8="","",_xludf.maxifs('Session Logs'!$E:$E,'Session Logs'!$D:$D,B8,'Session Logs'!$C:$C,D8)),"") | F8: =IFERROR(IF(A8="","",_xludf.maxifs('Session Logs'!$I:$I,'Session Logs'!$D:$D,B8,'Session Logs'!$C:$C,D8,'Session Logs'!$I:$I,">"&TODAY())),"") | G8: =IF(A8="","",IF(D8="","No Mentor Assigned",IF(E8="","No Sessions Yet",IF(AND(F8<>"",F8<TODAY()),"Missed Session",IF(AND(TODAY()-E8>30,F8=""),"Overdue – Book Now",IF(TODAY()-E8>30,"Overdue – Session Booked","On Track")))))) -> No Mentor Assigned
A9: ='Intern Profiles'!A9 -> F8884143 | B9: ='Intern Profiles'!B9 -> Nkhensani Shibambo | C9: ='Intern Profiles'!C9 -> Cohort 1 - 2026 | D9: =IF(A9="","",IFERROR(INDEX('Paste - Relationships'!$B$4:$B$800,MATCH(1,('Paste - Relationships'!$P$4:$P$800=VALUE(A9))*('Paste - Relationships'!$AE$4:$AE$800=""),0)),"")) | E9: =IFERROR(IF(A9="","",_xludf.maxifs('Session Logs'!$E:$E,'Session Logs'!$D:$D,B9,'Session Logs'!$C:$C,D9)),"") | F9: =IFERROR(IF(A9="","",_xludf.maxifs('Session Logs'!$I:$I,'Session Logs'!$D:$D,B9,'Session Logs'!$C:$C,D9,'Session Logs'!$I:$I,">"&TODAY())),"") | G9: =IF(A9="","",IF(D9="","No Mentor Assigned",IF(E9="","No Sessions Yet",IF(AND(F9<>"",F9<TODAY()),"Missed Session",IF(AND(TODAY()-E9>30,F9=""),"Overdue – Book Now",IF(TODAY()-E9>30,"Overdue – Session Booked","On Track")))))) -> No Mentor Assigned
A10: ='Intern Profiles'!A10 -> F8884358 | B10: ='Intern Profiles'!B10 -> Chesley Gustav | C10: ='Intern Profiles'!C10 -> Cohort 1 - 2026 | D10: =IF(A10="","",IFERROR(INDEX('Paste - Relationships'!$B$4:$B$800,MATCH(1,('Paste - Relationships'!$P$4:$P$800=VALUE(A10))*('Paste - Relationships'!$AE$4:$AE$800=""),0)),"")) | E10: =IFERROR(IF(A10="","",_xludf.maxifs('Session Logs'!$E:$E,'Session Logs'!$D:$D,B10,'Session Logs'!$C:$C,D10)),"") | F10: =IFERROR(IF(A10="","",_xludf.maxifs('Session Logs'!$I:$I,'Session Logs'!$D:$D,B10,'Session Logs'!$C:$C,D10,'Session Logs'!$I:$I,">"&TODAY())),"") | G10: =IF(A10="","",IF(D10="","No Mentor Assigned",IF(E10="","No Sessions Yet",IF(AND(F10<>"",F10<TODAY()),"Missed Session",IF(AND(TODAY()-E10>30,F10=""),"Overdue – Book Now",IF(TODAY()-E10>30,"Overdue – Session Booked","On Track")))))) -> No Mentor Assigned
A11: ='Intern Profiles'!A11 -> F8885583 | B11: ='Intern Profiles'!B11 -> Kgothatso Phillep Lebese | C11: ='Intern Profiles'!C11 -> Cohort 1 - 2026 | D11: =IF(A11="","",IFERROR(INDEX('Paste - Relationships'!$B$4:$B$800,MATCH(1,('Paste - Relationships'!$P$4:$P$800=VALUE(A11))*('Paste - Relationships'!$AE$4:$AE$800=""),0)),"")) | E11: =IFERROR(IF(A11="","",_xludf.maxifs('Session Logs'!$E:$E,'Session Logs'!$D:$D,B11,'Session Logs'!$C:$C,D11)),"") | F11: =IFERROR(IF(A11="","",_xludf.maxifs('Session Logs'!$I:$I,'Session Logs'!$D:$D,B11,'Session Logs'!$C:$C,D11,'Session Logs'!$I:$I,">"&TODAY())),"") | G11: =IF(A11="","",IF(D11="","No Mentor Assigned",IF(E11="","No Sessions Yet",IF(AND(F11<>"",F11<TODAY()),"Missed Session",IF(AND(TODAY()-E11>30,F11=""),"Overdue – Book Now",IF(TODAY()-E11>30,"Overdue – Session Booked","On Track")))))) -> No Mentor Assigned
A12: ='Intern Profiles'!A12 -> F8885759 | B12: ='Intern Profiles'!B12 -> Kgotatso Madela | C12: ='Intern Profiles'!C12 -> Cohort 1 - 2026 | D12: =IF(A12="","",IFERROR(INDEX('Paste - Relationships'!$B$4:$B$800,MATCH(1,('Paste - Relationships'!$P$4:$P$800=VALUE(A12))*('Paste - Relationships'!$AE$4:$AE$800=""),0)),"")) | E12: =IFERROR(IF(A12="","",_xludf.maxifs('Session Logs'!$E:$E,'Session Logs'!$D:$D,B12,'Session Logs'!$C:$C,D12)),"") | F12: =IFERROR(IF(A12="","",_xludf.maxifs('Session Logs'!$I:$I,'Session Logs'!$D:$D,B12,'Session Logs'!$C:$C,D12,'Session Logs'!$I:$I,">"&TODAY())),"") | G12: =IF(A12="","",IF(D12="","No Mentor Assigned",IF(E12="","No Sessions Yet",IF(AND(F12<>"",F12<TODAY()),"Missed Session",IF(AND(TODAY()-E12>30,F12=""),"Overdue – Book Now",IF(TODAY()-E12>30,"Overdue – Session Booked","On Track")))))) -> No Mentor Assigned
A13: ='Intern Profiles'!A13 -> F8885825 | B13: ='Intern Profiles'!B13 -> Noluthando Ndlovu | C13: ='Intern Profiles'!C13 -> Cohort 1 - 2026 | D13: =IF(A13="","",IFERROR(INDEX('Paste - Relationships'!$B$4:$B$800,MATCH(1,('Paste - Relationships'!$P$4:$P$800=VALUE(A13))*('Paste - Relationships'!$AE$4:$AE$800=""),0)),"")) | E13: =IFERROR(IF(A13="","",_xludf.maxifs('Session Logs'!$E:$E,'Session Logs'!$D:$D,B13,'Session Logs'!$C:$C,D13)),"") | F13: =IFERROR(IF(A13="","",_xludf.maxifs('Session Logs'!$I:$I,'Session Logs'!$D:$D,B13,'Session Logs'!$C:$C,D13,'Session Logs'!$I:$I,">"&TODAY())),"") | G13: =IF(A13="","",IF(D13="","No Mentor Assigned",IF(E13="","No Sessions Yet",IF(AND(F13<>"",F13<TODAY()),"Missed Session",IF(AND(TODAY()-E13>30,F13=""),"Overdue – Book Now",IF(TODAY()-E13>30,"Overdue – Session Booked","On Track")))))) -> No Mentor Assigned
A14: ='Intern Profiles'!A14 -> F8885615 | B14: ='Intern Profiles'!B14 -> Ncediwe Mphantsi | C14: ='Intern Profiles'!C14 -> Cohort 1 - 2026 | D14: =IF(A14="","",IFERROR(INDEX('Paste - Relationships'!$B$4:$B$800,MATCH(1,('Paste - Relationships'!$P$4:$P$800=VALUE(A14))*('Paste - Relationships'!$AE$4:$AE$800=""),0)),"")) | E14: =IFERROR(IF(A14="","",_xludf.maxifs('Session Logs'!$E:$E,'Session Logs'!$D:$D,B14,'Session Logs'!$C:$C,D14)),"") | F14: =IFERROR(IF(A14="","",_xludf.maxifs('Session Logs'!$I:$I,'Session Logs'!$D:$D,B14,'Session Logs'!$C:$C,D14,'Session Logs'!$I:$I,">"&TODAY())),"") | G14: =IF(A14="","",IF(D14="","No Mentor Assigned",IF(E14="","No Sessions Yet",IF(AND(F14<>"",F14<TODAY()),"Missed Session",IF(AND(TODAY()-E14>30,F14=""),"Overdue – Book Now",IF(TODAY()-E14>30,"Overdue – Session Booked","On Track")))))) -> No Mentor Assigned
A15: ='Intern Profiles'!A15 -> F8885674 | B15: ='Intern Profiles'!B15 -> Oratile Mathibe | C15: ='Intern Profiles'!C15 -> Cohort 1 - 2026 | D15: =IF(A15="","",IFERROR(INDEX('Paste - Relationships'!$B$4:$B$800,MATCH(1,('Paste - Relationships'!$P$4:$P$800=VALUE(A15))*('Paste - Relationships'!$AE$4:$AE$800=""),0)),"")) | E15: =IFERROR(IF(A15="","",_xludf.maxifs('Session Logs'!$E:$E,'Session Logs'!$D:$D,B15,'Session Logs'!$C:$C,D15)),"") | F15: =IFERROR(IF(A15="","",_xludf.maxifs('Session Logs'!$I:$I,'Session Logs'!$D:$D,B15,'Session Logs'!$C:$C,D15,'Session Logs'!$I:$I,">"&TODAY())),"") | G15: =IF(A15="","",IF(D15="","No Mentor Assigned",IF(E15="","No Sessions Yet",IF(AND(F15<>"",F15<TODAY()),"Missed Session",IF(AND(TODAY()-E15>30,F15=""),"Overdue – Book Now",IF(TODAY()-E15>30,"Overdue – Session Booked","On Track")))))) -> No Mentor Assigned
... A203: ='Intern Profiles'!A203 -> 0 | B203: ='Intern Profiles'!B203 -> 0 | C203: ='Intern Profiles'!C203 -> 0 | D203: =IF(A203="","",IFERROR(INDEX('Paste - Relationships'!$B$4:$B$800,MATCH(1,('Paste - Relationships'!$P$4:$P$800=VALUE(A203))*('Paste - Relationships'!$AE$4:$AE$800=""),0)),"")) | E203: =IFERROR(IF(A203="","",_xludf.maxifs('Session Logs'!$E:$E,'Session Logs'!$D:$D,B203,'Session Logs'!$C:$C,D203)),"") | F203: =IFERROR(IF(A203="","",_xludf.maxifs('Session Logs'!$I:$I,'Session Logs'!$D:$D,B203,'Session Logs'!$C:$C,D203,'Session Logs'!$I:$I,">"&TODAY())),"") | G203: =IF(A203="","",IF(D203="","No Mentor Assigned",IF(E203="","No Sessions Yet",IF(AND(F203<>"",F203<TODAY()),"Missed Session",IF(AND(TODAY()-E203>30,F203=""),"Overdue – Book Now",IF(TODAY()-E203>30,"Overdue – Session Booked","On Track")))))) -> No Mentor Assigned

Sheet Session Logs
A1: Total Sessions Logged: | B1: =COUNTA(A3:A4997) -> 1 | D1: Sessions This Month: | E1: =COUNTIFS(E2:E4997,">="&DATE(YEAR(TODAY()),MONTH(TODAY()),1),E2:E4997,"<="&TODAY()) -> 0 | H1: Concerns Flagged: | I1: =COUNTIF(K2:K4997,"Yes") -> 0
A2: Timestamp (Form Auto) | B2: Submitted By (Role) | C2: Mentor Name | D2: Intern Name | E2: Session Date | F2: Duration (mins) | G2: Key Discussion Points | H2: Action Items / Takeaways | I2: Next Session Planned Date | J2: Next Session Focus | K2: Concern Flagged? (Yes/No) | L2: Concern Details
A3: ← Paste form data here

Sheet Monthly Pulse Logs
A1: Total Responses: | B1: =COUNTA(A3:A4997) -> 1 | D1: Avg Meeting Value: | E1: =IFERROR(AVERAGE(F2:F4997),"–") -> – | G1: Avg Goal Progress: | H1: =IFERROR(AVERAGE(G2:G4997),"–") -> – | J1: Avg Support Felt: | K1: =IFERROR(AVERAGE(H2:H4997),"–") -> – | M1: Concerns Raised: | N1: =COUNTIF(M2:M4997,"Yes") -> 0
A2: Timestamp (Form Auto) | B2: Respondent Name | C2: Role (Mentor/Intern) | D2: Cohort | E2: Mentor/Intern Pair | F2: Q1: Meeting Value (1-5) | G2: Q2: Goal Progress (1-5) | H2: Q3: Support Felt (1-5) | I2: Q4: Next Steps Clarity (1-5) | J2: Sessions This Month | K2: What's Working Well | L2: What Would Make It Better | M2: Concern Flagged? (Yes/No) | N2: Concern / Support Needed
A3: ← Paste form data here
